{
  "13125": {
    "1": {
      "0": [0, 1, 1],
      "2": [0, 1, 1],
      "4": [0, 1, 1],
      "6": [0, 1, 1],
      "8": [0, 1, 1]
    },
    "4": {
      "0": [0, 0, 1],
      "2": [0, 0, 1],
      "4": [0, 0, 1],
      "6": [0, 0, 1],
      "8": [0, 0, 1]
    },
    "6": {
      "0": [0, 0, 1],
      "2": [0, 0, 1],
      "4": [0, 0, 1],
      "6": [0, 0, 1],
      "8": [0, 0, 1]
    },
    "8": {
      "0": [0, 0, 1],
      "2": [0, 0, 1],
      "4": [0, 0, 1],
      "6": [0, 0, 1],
      "8": [0, 0, 1]
    },
    "10": {
      "0": [0, 0, 1],
      "2": [0, 0, 1],
      "4": [0, 0, 1],
      "6": [0, 0, 1],
      "8": [0, 0, 1]
    },
    "17": {
      "0": [0, 0, 1],
      "2": [0, 0, 1],
      "4": [0, 0, 1],
      "6": [0, 0, 1],
      "8": [0, 0, 1]
    },
    "18": {
      "0": [0, 0, 1],
      "2": [0, 0, 1],
      "4": [0, 0, 1],
      "6": [0, 0, 1],
      "8": [0, 0, 1]
    },
    "19": {
      "0": [0, 0, 1],
      "2": [0, 0, 1],
      "4": [0, 0, 1],
      "6": [0, 0, 1],
      "8": [0, 0, 1]
    },
    "20": {
      "0": [0, 0, 1],
      "2": [0, 0, 1],
      "4": [0, 0, 1],
      "6": [0, 0, 1],
      "8": [0, 0, 1]
    },
    "21": {
      "0": [0, 0, 1],
      "2": [0, 0, 1],
      "4": [0, 0, 1],
      "6": [0, 0, 1],
      "8": [0, 0, 1]
    },
    "22": {
      "0": [0, 0, 1],
      "2": [0, 0, 1],
      "4": [0, 0, 1],
      "6": [0, 0, 1],
      "8": [0, 0, 1]
    },
    "23": {
      "0": [0, 0, 1],
      "2": [0, 0, 1],
      "4": [0, 0, 1],
      "6": [0, 0, 1],
      "8": [0, 0, 1]
    },
    "24": {
      "0": [0, 0, 1],
      "2": [0, 0, 1],
      "4": [0, 0, 1],
      "6": [0, 0, 1],
      "8": [0, 0, 1]
    },
    "25": {
      "0": [0, 0, 1],
      "2": [0, 0, 1],
      "4": [0, 0, 1],
      "6": [0, 0, 1],
      "8": [0, 0, 1]
    },
    "26": {
      "0": [0, 0, 1],
      "2": [0, 0, 1],
      "4": [0, 0, 1],
      "6": [0, 0, 1],
      "8": [0, 0, 1]
    },
    "27": {
      "0": [0, 0, 1],
      "2": [0, 0, 1],
      "4": [0, 0, 1],
      "6": [0, 0, 1],
      "8": [0, 0, 1]
    },
    "28": {
      "0": [0, 0, 1],
      "2": [0, 0, 1],
      "4": [0, 0, 1],
      "6": [0, 0, 1],
      "8": [0, 0, 1]
    },
    "29": { "0": [0, 0, 1], "2": [0, 0, 1], "4": [0, 0, 1] },
    "30": { "0": [0, 0, 1], "2": [0, 0, 1], "4": [0, 0, 1] },
    "31": { "0": [0, 0, 1], "2": [0, 0, 1], "4": [0, 0, 1] },
    "32": { "0": [0, 0, 1], "2": [0, 0, 1], "4": [0, 0, 1] },
    "33": {
      "0": [0, 0, 1],
      "2": [0, 0, 1],
      "4": [0, 0, 1],
      "6": [0, 0, 1],
      "8": [0, 0, 1]
    },
    "34": { "0": [0, 0, 1], "2": [0, 0, 1], "4": [0, 0, 1] },
    "35": {
      "0": [0, 0, 1],
      "2": [0, 0, 1],
      "4": [0, 0, 1],
      "6": [0, 0, 1],
      "8": [0, 0, 1]
    },
    "36": {
      "0": [0, 0, 1],
      "2": [0, 0, 1],
      "4": [0, 0, 1],
      "6": [0, 0, 1],
      "8": [0, 0, 1]
    },
    "37": {
      "0": [0, 0, 1],
      "2": [0, 0, 1],
      "4": [0, 0, 1],
      "6": [0, 0, 1],
      "8": [0, 0, 1]
    },
    "38": {
      "0": [0, 0, 1],
      "2": [0, 0, 1],
      "4": [0, 0, 1],
      "6": [0, 0, 1],
      "8": [0, 0, 1]
    },
    "39": {
      "0": [0, 0, 1],
      "2": [0, 0, 1],
      "4": [0, 0, 1],
      "6": [0, 0, 1],
      "8": [0, 0, 1]
    },
    "40": {
      "0": [0, 0, 1],
      "2": [0, 0, 1],
      "4": [0, 0, 1],
      "6": [0, 0, 1],
      "8": [0, 0, 1]
    },
    "41": {
      "0": [0, 0, 1],
      "2": [0, 0, 1],
      "4": [0, 0, 1],
      "6": [0, 0, 1],
      "8": [0, 0, 1]
    },
    "52": {
      "0": [0, 0, 1],
      "2": [0, 0, 1],
      "4": [0, 0, 1],
      "6": [0, 0, 1],
      "8": [0, 0, 1]
    },
    "58": {
      "0": [0, 0, 1],
      "2": [0, 0, 1],
      "4": [0, 0, 1],
      "6": [0, 0, 1],
      "8": [0, 0, 1]
    },
    "60": {
      "0": [0, 0, 1],
      "2": [0, 0, 1],
      "4": [0, 0, 1],
      "6": [0, 0, 1],
      "8": [0, 0, 1]
    },
    "61": {
      "0": [0, 1, 1],
      "2": [0, 1, 1],
      "4": [0, 0, 1],
      "6": [0, 0, 1],
      "8": [0, 0, 1]
    },
    "62": {
      "0": [0, 1, 1],
      "2": [0, 1, 1],
      "4": [0, 1, 1],
      "6": [0, 1, 1],
      "8": [0, 1, 1]
    },
    "1A": {
      "0": [0, 1, 1],
      "2": [0, 1, 1],
      "4": [0, 1, 1],
      "6": [0, 1, 1],
      "8": [0, 1, 1]
    },
    "31G": { "6": [0, 0, 1], "8": [0, 0, 1] },
    "10A": {
      "0": [0, 0, 1],
      "2": [0, 0, 1],
      "4": [0, 0, 1],
      "6": [0, 0, 1],
      "8": [0, 0, 1]
    },
    "18A": {
      "0": [0, 0, 1],
      "2": [0, 0, 1],
      "4": [0, 0, 1],
      "6": [0, 0, 1],
      "8": [0, 0, 1]
    },
    "19A": {
      "0": [0, 0, 1],
      "2": [0, 0, 1],
      "4": [0, 0, 1],
      "6": [0, 0, 1],
      "8": [0, 0, 1]
    },
    "22A": {
      "0": [0, 0, 1],
      "2": [0, 0, 1],
      "4": [0, 0, 1],
      "6": [0, 0, 1],
      "8": [0, 0, 1]
    },
    "24A": {
      "0": [0, 0, 1],
      "2": [0, 0, 1],
      "4": [0, 0, 1],
      "6": [0, 0, 1],
      "8": [0, 0, 1]
    },
    "41A": {
      "0": [0, 0, 1],
      "2": [0, 0, 1],
      "4": [0, 0, 1],
      "6": [0, 0, 1],
      "8": [0, 0, 1]
    },
    "41B": {
      "0": [0, 0, 1],
      "2": [0, 0, 1],
      "4": [0, 0, 1],
      "6": [0, 0, 1],
      "8": [0, 0, 1]
    },
    "41C": {
      "0": [0, 0, 1],
      "2": [0, 0, 1],
      "4": [0, 0, 1],
      "6": [0, 0, 1],
      "8": [0, 0, 1]
    },
    "41D": {
      "0": [0, 0, 1],
      "2": [0, 0, 1],
      "4": [0, 0, 1],
      "6": [0, 0, 1],
      "8": [0, 0, 1]
    },
    "41E": {
      "0": [0, 0, 1],
      "2": [0, 0, 1],
      "4": [0, 0, 1],
      "6": [0, 0, 1],
      "8": [0, 0, 1]
    },
    "41F": {
      "0": [0, 0, 1],
      "2": [0, 0, 1],
      "4": [0, 0, 1],
      "6": [0, 0, 1],
      "8": [0, 0, 1]
    },
    "41G": {
      "0": [0, 0, 1],
      "2": [0, 0, 1],
      "4": [0, 0, 1],
      "6": [0, 0, 1],
      "8": [0, 0, 1]
    },
    "41H": {
      "0": [0, 0, 1],
      "2": [0, 0, 1],
      "4": [0, 0, 1],
      "6": [0, 0, 1],
      "8": [0, 0, 1]
    },
    "41J": {
      "0": [0, 0, 1],
      "2": [0, 0, 1],
      "4": [0, 0, 1],
      "6": [0, 0, 1],
      "8": [0, 0, 1]
    },
    "41K": {
      "0": [0, 0, 1],
      "2": [0, 0, 1],
      "4": [0, 0, 1],
      "6": [0, 0, 1],
      "8": [0, 0, 1]
    },
    "41L": {
      "0": [0, 0, 1],
      "2": [0, 0, 1],
      "4": [0, 0, 1],
      "6": [0, 0, 1],
      "8": [0, 0, 1]
    },
    "41M": {
      "0": [0, 0, 1],
      "2": [0, 0, 1],
      "4": [0, 0, 1],
      "6": [0, 0, 1],
      "8": [0, 0, 1]
    },
    "26A": { "6": [0, 0, 1], "8": [0, 0, 1] },
    "29A": { "6": [0, 0, 1], "8": [0, 0, 1] },
    "29B": { "6": [0, 0, 1], "8": [0, 0, 1] },
    "29C": { "6": [0, 0, 1], "8": [0, 0, 1] },
    "29D": { "6": [0, 0, 1], "8": [0, 0, 1] },
    "29E": { "6": [0, 0, 1], "8": [0, 0, 1] },
    "29F": { "6": [0, 0, 1], "8": [0, 0, 1] },
    "29G": { "6": [0, 0, 1], "8": [0, 0, 1] },
    "29H": { "6": [0, 0, 1], "8": [0, 0, 1] },
    "30A": { "6": [0, 0, 1], "8": [0, 0, 1] },
    "30B": { "6": [0, 0, 1], "8": [0, 0, 1] },
    "30C": { "6": [0, 0, 1], "8": [0, 0, 1] },
    "30D": { "6": [0, 0, 1], "8": [0, 0, 1] },
    "30E": { "6": [0, 0, 1], "8": [0, 0, 1] },
    "30F": { "6": [0, 0, 1], "8": [0, 0, 1] },
    "30G": { "6": [0, 0, 1], "8": [0, 0, 1] },
    "30H": { "6": [0, 0, 1], "8": [0, 0, 1] },
    "31A": { "6": [0, 0, 1], "8": [0, 0, 1] },
    "31B": { "6": [0, 0, 1], "8": [0, 0, 1] },
    "31C": { "6": [0, 0, 1], "8": [0, 0, 1] },
    "31D": { "6": [0, 0, 1], "8": [0, 0, 1] },
    "31E": { "6": [0, 0, 1], "8": [0, 0, 1] },
    "31F": { "6": [0, 0, 1], "8": [0, 0, 1] },
    "31H": { "6": [0, 0, 1], "8": [0, 0, 1] },
    "32A": { "6": [0, 0, 1], "8": [0, 0, 1] },
    "32B": { "6": [0, 0, 1], "8": [0, 0, 1] },
    "33A": { "6": [0, 0, 1], "8": [0, 0, 1] },
    "33B": { "6": [0, 0, 1], "8": [0, 0, 1] },
    "33C": { "6": [0, 0, 1], "8": [0, 0, 1] },
    "33D": { "6": [0, 0, 1], "8": [0, 0, 1] },
    "33E": { "6": [0, 0, 1], "8": [0, 0, 1] },
    "33F": { "6": [0, 0, 1], "8": [0, 0, 1] },
    "34A": { "6": [0, 0, 1], "8": [0, 0, 1] },
    "34B": { "6": [0, 0, 1], "8": [0, 0, 1] },
    "34C": { "6": [0, 0, 1], "8": [0, 0, 1] },
    "34D": { "6": [0, 0, 1], "8": [0, 0, 1] },
    "34E": { "6": [0, 0, 1], "8": [0, 0, 1] },
    "34F": { "6": [0, 0, 1], "8": [0, 0, 1] },
    "34G": { "6": [0, 0, 1], "8": [0, 0, 1] },
    "34H": { "6": [0, 0, 1], "8": [0, 0, 1] }
  }
}
