{
  "13503": {
    "1": {
      "0": [1, 1, 0],
      "2": [1, 1, 0],
      "4": [1, 1, 0],
      "6": [1, 1, 0],
      "8": [1, 1, 0]
    },
    "2": {
      "0": [1, 1, 0],
      "2": [1, 1, 0],
      "4": [1, 1, 0],
      "6": [1, 1, 0],
      "8": [1, 1, 0]
    },
    "3": {
      "0": [1, 1, 0],
      "2": [1, 1, 0],
      "4": [1, 1, 0],
      "6": [1, 1, 0],
      "8": [1, 1, 0]
    },
    "4": {
      "0": [1, 1, 0],
      "2": [1, 1, 0],
      "4": [1, 1, 0],
      "6": [1, 1, 0],
      "8": [1, 1, 0]
    },
    "5": {
      "0": [1, 1, 0],
      "2": [1, 1, 0],
      "4": [1, 1, 0],
      "6": [1, 1, 0],
      "8": [1, 1, 0]
    },
    "7": {
      "0": [1, 1, 0],
      "2": [1, 1, 0],
      "4": [1, 1, 0],
      "6": [1, 1, 0],
      "8": [1, 1, 0]
    },
    "8": {
      "0": [1, 1, 0],
      "2": [1, 1, 0],
      "4": [1, 1, 0],
      "6": [1, 1, 0],
      "8": [1, 1, 0]
    },
    "9": {
      "0": [1, 1, 0],
      "2": [1, 1, 0],
      "4": [1, 1, 0],
      "6": [1, 1, 0],
      "8": [1, 1, 0]
    },
    "10": {
      "0": [1, 1, 0],
      "2": [1, 1, 0],
      "4": [1, 1, 0],
      "6": [1, 1, 0],
      "8": [1, 1, 0]
    },
    "11": {
      "0": [1, 0, 0],
      "2": [1, 0, 0],
      "4": [1, 0, 0],
      "6": [1, 0, 0],
      "8": [1, 0, 0]
    },
    "12": {
      "0": [1, 1, 0],
      "2": [1, 1, 0],
      "4": [1, 1, 0],
      "6": [1, 1, 0],
      "8": [1, 1, 0]
    },
    "13": {
      "0": [1, 1, 0],
      "2": [1, 1, 0],
      "4": [1, 1, 0],
      "6": [1, 1, 0],
      "8": [1, 1, 0]
    },
    "14": {
      "0": [1, 1, 0],
      "2": [1, 1, 0],
      "4": [1, 1, 0],
      "6": [1, 1, 0],
      "8": [1, 1, 0]
    },
    "15": {
      "0": [1, 0, 0],
      "2": [1, 0, 0],
      "4": [1, 0, 0],
      "6": [1, 0, 0],
      "8": [1, 0, 0]
    },
    "16": {
      "0": [1, 1, 0],
      "2": [1, 1, 0],
      "4": [1, 1, 0],
      "6": [1, 1, 0],
      "8": [1, 1, 0]
    },
    "17": {
      "0": [1, 1, 0],
      "2": [1, 1, 0],
      "4": [1, 1, 0],
      "6": [1, 1, 0],
      "8": [1, 1, 0]
    },
    "18": {
      "0": [1, 1, 0],
      "2": [1, 1, 0],
      "4": [1, 1, 0],
      "6": [1, 1, 0],
      "8": [1, 1, 0]
    },
    "19": {
      "0": [1, 1, 0],
      "2": [1, 1, 0],
      "4": [1, 1, 0],
      "6": [1, 1, 0],
      "8": [1, 1, 0]
    },
    "20": {
      "0": [1, 1, 0],
      "2": [1, 1, 0],
      "4": [1, 1, 0],
      "6": [1, 1, 0],
      "8": [1, 1, 0]
    },
    "21": {
      "0": [1, 1, 0],
      "2": [1, 1, 0],
      "4": [1, 1, 0],
      "6": [1, 1, 0],
      "8": [1, 1, 0]
    },
    "22": {
      "0": [1, 0, 0],
      "2": [1, 0, 0],
      "4": [1, 0, 0],
      "6": [1, 0, 0],
      "8": [1, 0, 0]
    },
    "23": {
      "0": [1, 1, 0],
      "2": [1, 1, 0],
      "4": [1, 1, 0],
      "6": [1, 1, 0],
      "8": [1, 1, 0]
    },
    "24": {
      "0": [1, 1, 0],
      "2": [1, 1, 0],
      "4": [1, 1, 0],
      "6": [1, 1, 0],
      "8": [1, 1, 0]
    },
    "25": {
      "0": [1, 0, 0],
      "2": [1, 0, 0],
      "4": [1, 0, 0],
      "6": [1, 0, 0],
      "8": [1, 0, 0]
    },
    "26": {
      "0": [1, 1, 0],
      "2": [1, 1, 0],
      "4": [1, 1, 0],
      "6": [1, 1, 0],
      "8": [1, 1, 0]
    },
    "27": {
      "0": [1, 1, 0],
      "2": [1, 1, 0],
      "4": [1, 1, 0],
      "6": [1, 1, 0],
      "8": [1, 1, 0]
    },
    "28": {
      "0": [1, 1, 0],
      "2": [1, 1, 0],
      "4": [1, 1, 0],
      "6": [1, 1, 0],
      "8": [1, 1, 0]
    },
    "29": {
      "0": [1, 1, 0],
      "2": [1, 1, 0],
      "4": [1, 1, 0],
      "6": [1, 1, 0],
      "8": [1, 1, 0]
    },
    "30": {
      "0": [1, 1, 0],
      "2": [1, 1, 0],
      "4": [1, 1, 0],
      "6": [1, 1, 0],
      "8": [1, 1, 0]
    },
    "31": {
      "0": [1, 1, 0],
      "2": [1, 1, 0],
      "4": [1, 1, 0],
      "6": [1, 1, 0],
      "8": [1, 1, 0]
    },
    "32": {
      "0": [1, 1, 0],
      "2": [1, 1, 0],
      "4": [1, 1, 0],
      "6": [1, 1, 0],
      "8": [1, 1, 0]
    },
    "33": {
      "0": [1, 1, 0],
      "2": [1, 1, 0],
      "4": [1, 1, 0],
      "6": [1, 1, 0],
      "8": [1, 1, 0]
    },
    "34": {
      "0": [1, 1, 0],
      "2": [1, 1, 0],
      "4": [1, 1, 0],
      "6": [1, 1, 0],
      "8": [1, 1, 0]
    },
    "35": {
      "0": [1, 1, 0],
      "2": [1, 1, 0],
      "4": [1, 1, 0],
      "6": [1, 1, 0],
      "8": [1, 1, 0]
    },
    "36": {
      "0": [1, 0, 0],
      "2": [1, 0, 0],
      "4": [1, 0, 0],
      "6": [1, 0, 0],
      "8": [1, 0, 0]
    },
    "37": {
      "0": [1, 1, 0],
      "2": [1, 1, 0],
      "4": [1, 1, 0],
      "6": [1, 1, 0],
      "8": [1, 1, 0]
    },
    "38": {
      "0": [1, 1, 0],
      "2": [1, 1, 0],
      "4": [1, 1, 0],
      "6": [1, 1, 0],
      "8": [1, 1, 0]
    },
    "39": {
      "0": [1, 1, 0],
      "2": [1, 1, 0],
      "4": [1, 1, 0],
      "6": [1, 1, 0],
      "8": [1, 1, 0]
    },
    "40": {
      "0": [1, 1, 0],
      "2": [1, 1, 0],
      "4": [1, 1, 0],
      "6": [1, 1, 0],
      "8": [1, 1, 0]
    },
    "41": {
      "0": [1, 1, 0],
      "2": [1, 1, 0],
      "4": [1, 1, 0],
      "6": [1, 1, 0],
      "8": [1, 1, 0]
    },
    "42": {
      "0": [1, 0, 0],
      "2": [1, 0, 0],
      "4": [1, 0, 0],
      "6": [1, 0, 0],
      "8": [1, 0, 0]
    },
    "43": {
      "0": [1, 0, 0],
      "2": [1, 0, 0],
      "4": [1, 0, 0],
      "6": [1, 0, 0],
      "8": [1, 0, 0]
    },
    "44": {
      "0": [1, 1, 0],
      "2": [1, 1, 0],
      "4": [1, 1, 0],
      "6": [1, 1, 0],
      "8": [1, 1, 0]
    },
    "45": {
      "0": [1, 1, 0],
      "2": [1, 1, 0],
      "4": [1, 1, 0],
      "6": [1, 1, 0],
      "8": [1, 1, 0]
    },
    "46": {
      "0": [1, 1, 0],
      "2": [1, 1, 0],
      "4": [1, 1, 0],
      "6": [1, 1, 0],
      "8": [1, 1, 0]
    },
    "47": {
      "0": [1, 1, 0],
      "2": [1, 1, 0],
      "4": [1, 1, 0],
      "6": [1, 1, 0],
      "8": [1, 1, 0]
    },
    "48": {
      "0": [1, 1, 0],
      "2": [1, 1, 0],
      "4": [1, 1, 0],
      "6": [1, 1, 0],
      "8": [1, 1, 0]
    },
    "49": {
      "0": [1, 0, 0],
      "2": [1, 0, 0],
      "4": [1, 0, 0],
      "6": [1, 0, 0],
      "8": [1, 0, 0]
    },
    "50": {
      "0": [1, 1, 0],
      "2": [1, 1, 0],
      "4": [1, 1, 0],
      "6": [1, 1, 0],
      "8": [1, 1, 0]
    },
    "51": {
      "0": [1, 1, 0],
      "2": [1, 1, 0],
      "4": [1, 1, 0],
      "6": [1, 1, 0],
      "8": [1, 1, 0]
    },
    "52": {
      "0": [1, 1, 0],
      "2": [1, 1, 0],
      "4": [1, 1, 0],
      "6": [1, 1, 0],
      "8": [1, 1, 0]
    },
    "53": {
      "0": [1, 0, 0],
      "2": [1, 0, 0],
      "4": [1, 0, 0],
      "6": [1, 0, 0],
      "8": [1, 0, 0]
    },
    "54": {
      "0": [1, 1, 0],
      "2": [1, 1, 0],
      "4": [1, 1, 0],
      "6": [1, 1, 0],
      "8": [1, 1, 0]
    },
    "55": {
      "0": [1, 0, 0],
      "2": [1, 0, 0],
      "4": [1, 0, 0],
      "6": [1, 0, 0],
      "8": [1, 0, 0]
    },
    "57": {
      "0": [1, 1, 0],
      "2": [1, 1, 0],
      "4": [1, 1, 0],
      "6": [1, 1, 0],
      "8": [1, 1, 0]
    },
    "58": {
      "0": [1, 1, 0],
      "2": [1, 1, 0],
      "4": [1, 1, 0],
      "6": [1, 1, 0],
      "8": [1, 1, 0]
    },
    "59": {
      "0": [1, 0, 0],
      "2": [1, 0, 0],
      "4": [1, 0, 0],
      "6": [1, 0, 0],
      "8": [1, 0, 0]
    },
    "60": {
      "0": [1, 1, 0],
      "2": [1, 1, 0],
      "4": [1, 1, 0],
      "6": [1, 1, 0],
      "8": [1, 1, 0]
    },
    "61": {
      "0": [1, 1, 0],
      "2": [1, 1, 0],
      "4": [1, 1, 0],
      "6": [1, 1, 0],
      "8": [1, 1, 0]
    },
    "62": {
      "0": [1, 1, 0],
      "2": [1, 1, 0],
      "4": [1, 1, 0],
      "6": [1, 1, 0],
      "8": [1, 1, 0]
    },
    "63": {
      "0": [1, 1, 0],
      "2": [1, 1, 0],
      "4": [1, 1, 0],
      "6": [1, 1, 0],
      "8": [1, 1, 0]
    },
    "64": {
      "0": [1, 1, 0],
      "2": [1, 1, 0],
      "4": [1, 1, 0],
      "6": [1, 1, 0],
      "8": [1, 1, 0]
    },
    "66": {
      "0": [1, 1, 0],
      "2": [1, 1, 0],
      "4": [1, 1, 0],
      "6": [1, 1, 0],
      "8": [1, 1, 0]
    },
    "68": {
      "0": [1, 1, 0],
      "2": [1, 1, 0],
      "4": [1, 1, 0],
      "6": [1, 1, 0],
      "8": [1, 1, 0]
    },
    "70": {
      "0": [1, 1, 0],
      "2": [1, 1, 0],
      "4": [1, 1, 0],
      "6": [1, 1, 0],
      "8": [1, 1, 0]
    },
    "72": {
      "0": [1, 1, 0],
      "2": [1, 1, 0],
      "4": [1, 1, 0],
      "6": [1, 1, 0],
      "8": [1, 1, 0]
    },
    "74": {
      "0": [1, 1, 0],
      "2": [1, 1, 0],
      "4": [1, 1, 0],
      "6": [1, 1, 0],
      "8": [1, 1, 0]
    },
    "76": {
      "0": [1, 0, 0],
      "2": [1, 0, 0],
      "4": [1, 1, 0],
      "6": [1, 1, 0],
      "8": [1, 1, 0]
    },
    "78": {
      "0": [1, 1, 0],
      "2": [1, 1, 0],
      "4": [1, 0, 0],
      "6": [1, 0, 0],
      "8": [1, 0, 0]
    },
    "80": {
      "0": [1, 1, 0],
      "2": [1, 1, 0],
      "4": [1, 1, 0],
      "6": [1, 1, 0],
      "8": [1, 1, 0]
    },
    "82": {
      "0": [1, 1, 0],
      "2": [1, 1, 0],
      "4": [1, 1, 0],
      "6": [1, 1, 0],
      "8": [1, 1, 0]
    },
    "84": {
      "0": [1, 0, 0],
      "2": [1, 0, 0],
      "4": [1, 0, 0],
      "6": [1, 0, 0],
      "8": [1, 0, 0]
    },
    "86": {
      "0": [1, 1, 0],
      "2": [1, 1, 0],
      "4": [1, 1, 0],
      "6": [1, 1, 0],
      "8": [1, 1, 0]
    },
    "88": {
      "0": [1, 0, 0],
      "2": [1, 0, 0],
      "4": [1, 0, 0],
      "6": [1, 0, 0],
      "8": [1, 0, 0]
    },
    "90": {
      "0": [1, 0, 0],
      "2": [1, 0, 0],
      "4": [1, 0, 0],
      "6": [1, 0, 0],
      "8": [1, 0, 0]
    },
    "92": {
      "0": [1, 1, 0],
      "2": [1, 1, 0],
      "4": [1, 1, 0],
      "6": [1, 1, 0],
      "8": [1, 1, 0]
    },
    "94": {
      "0": [1, 0, 0],
      "2": [1, 0, 0],
      "4": [1, 0, 0],
      "6": [1, 0, 0],
      "8": [1, 0, 0]
    },
    "96": {
      "0": [1, 1, 0],
      "2": [1, 1, 0],
      "4": [1, 1, 0],
      "6": [1, 1, 0],
      "8": [1, 1, 0]
    },
    "98": {
      "0": [1, 1, 0],
      "2": [1, 1, 0],
      "4": [1, 0, 0],
      "6": [1, 0, 0],
      "8": [1, 0, 0]
    },
    "100": {
      "0": [1, 1, 0],
      "2": [1, 1, 0],
      "4": [1, 1, 0],
      "6": [1, 1, 0],
      "8": [1, 1, 0]
    },
    "102": {
      "0": [1, 1, 0],
      "2": [1, 1, 0],
      "4": [1, 0, 0],
      "6": [1, 0, 0],
      "8": [1, 0, 0]
    },
    "104": {
      "0": [1, 0, 0],
      "2": [1, 0, 0],
      "4": [1, 0, 0],
      "6": [1, 0, 0],
      "8": [1, 0, 0]
    },
    "106": {
      "0": [1, 0, 0],
      "2": [1, 0, 0],
      "4": [1, 0, 0],
      "6": [1, 0, 0],
      "8": [1, 0, 0]
    },
    "108": {
      "0": [1, 0, 0],
      "2": [1, 0, 0],
      "4": [1, 0, 0],
      "6": [1, 0, 0],
      "8": [1, 0, 0]
    },
    "110": {
      "0": [1, 0, 0],
      "2": [1, 0, 0],
      "4": [1, 0, 0],
      "6": [1, 0, 0],
      "8": [1, 0, 0]
    },
    "112": {
      "0": [1, 1, 0],
      "2": [1, 1, 0],
      "4": [1, 1, 0],
      "6": [1, 1, 0],
      "8": [1, 1, 0]
    },
    "120": {
      "0": [1, 1, 0],
      "2": [1, 1, 0],
      "4": [1, 1, 0],
      "6": [1, 1, 0],
      "8": [1, 1, 0]
    },
    "121": {
      "0": [1, 1, 0],
      "2": [1, 1, 0],
      "4": [1, 1, 0],
      "6": [1, 1, 0],
      "8": [1, 1, 0]
    },
    "122": {
      "0": [1, 1, 0],
      "2": [1, 1, 0],
      "4": [1, 1, 0],
      "6": [1, 1, 0],
      "8": [1, 1, 0]
    },
    "123": {
      "0": [1, 0, 0],
      "2": [1, 0, 0],
      "4": [1, 0, 0],
      "6": [1, 0, 0],
      "8": [1, 0, 0]
    },
    "124": {
      "0": [1, 1, 0],
      "2": [1, 1, 0],
      "4": [1, 1, 0],
      "6": [1, 1, 0],
      "8": [1, 1, 0]
    },
    "125": {
      "0": [1, 1, 0],
      "2": [1, 1, 0],
      "4": [1, 1, 0],
      "6": [1, 1, 0],
      "8": [1, 1, 0]
    },
    "126": {
      "0": [1, 1, 0],
      "2": [1, 1, 0],
      "4": [1, 1, 0],
      "6": [1, 1, 0],
      "8": [1, 1, 0]
    },
    "127": {
      "0": [1, 1, 0],
      "2": [1, 1, 0],
      "4": [1, 1, 0],
      "6": [1, 1, 0],
      "8": [1, 1, 0]
    },
    "129": {
      "0": [1, 1, 0],
      "2": [1, 1, 0],
      "4": [1, 1, 0],
      "6": [1, 1, 0],
      "8": [1, 1, 0]
    },
    "130": {
      "0": [1, 1, 0],
      "2": [1, 1, 0],
      "4": [1, 1, 0],
      "6": [1, 1, 0],
      "8": [1, 1, 0]
    },
    "131": {
      "0": [1, 1, 0],
      "2": [1, 1, 0],
      "4": [1, 1, 0],
      "6": [1, 1, 0],
      "8": [1, 1, 0]
    },
    "132": {
      "0": [1, 1, 0],
      "2": [1, 1, 0],
      "4": [1, 1, 0],
      "6": [1, 1, 0],
      "8": [1, 1, 0]
    },
    "133": {
      "0": [1, 0, 0],
      "2": [1, 0, 0],
      "4": [1, 0, 0],
      "6": [1, 0, 0],
      "8": [1, 0, 0]
    },
    "134": {
      "0": [1, 1, 0],
      "2": [1, 1, 0],
      "4": [1, 1, 0],
      "6": [1, 1, 0],
      "8": [1, 1, 0]
    },
    "135": {
      "0": [1, 1, 0],
      "2": [1, 1, 0],
      "4": [1, 1, 0],
      "6": [1, 1, 0],
      "8": [1, 1, 0]
    },
    "136": {
      "0": [1, 1, 0],
      "2": [1, 1, 0],
      "4": [1, 1, 0],
      "6": [1, 1, 0],
      "8": [1, 1, 0]
    },
    "137": {
      "0": [1, 1, 0],
      "2": [1, 1, 0],
      "4": [1, 0, 0],
      "6": [1, 0, 0],
      "8": [1, 0, 0]
    },
    "139": {
      "0": [1, 0, 0],
      "2": [1, 0, 0],
      "4": [1, 0, 0],
      "6": [1, 0, 0],
      "8": [1, 0, 0]
    },
    "141": {
      "0": [1, 0, 0],
      "2": [1, 0, 0],
      "4": [1, 0, 0],
      "6": [1, 0, 0],
      "8": [1, 0, 0]
    },
    "142": {
      "0": [1, 1, 0],
      "2": [1, 1, 0],
      "4": [1, 1, 0],
      "6": [1, 1, 0],
      "8": [1, 1, 0]
    },
    "143": {
      "0": [1, 1, 0],
      "2": [1, 1, 0],
      "4": [1, 0, 0],
      "6": [1, 0, 0],
      "8": [1, 0, 0]
    },
    "144": {
      "0": [1, 0, 0],
      "2": [1, 0, 0],
      "4": [1, 0, 0],
      "6": [1, 0, 0],
      "8": [1, 0, 0]
    },
    "145": {
      "0": [1, 1, 0],
      "2": [1, 1, 0],
      "4": [1, 1, 0],
      "6": [1, 1, 0],
      "8": [1, 1, 0]
    },
    "146": {
      "0": [1, 1, 0],
      "2": [1, 1, 0],
      "4": [1, 1, 0],
      "6": [1, 1, 0],
      "8": [1, 1, 0]
    },
    "147": {
      "0": [1, 1, 0],
      "2": [1, 1, 0],
      "4": [1, 1, 0],
      "6": [1, 1, 0],
      "8": [1, 1, 0]
    },
    "148": {
      "0": [1, 1, 0],
      "2": [1, 1, 0],
      "4": [1, 1, 0],
      "6": [1, 1, 0],
      "8": [1, 1, 0]
    },
    "149": {
      "0": [1, 1, 0],
      "2": [1, 1, 0],
      "4": [1, 1, 0],
      "6": [1, 1, 0],
      "8": [1, 1, 0]
    },
    "150": {
      "0": [1, 1, 0],
      "2": [1, 1, 0],
      "4": [1, 1, 0],
      "6": [1, 1, 0],
      "8": [1, 1, 0]
    },
    "151": {
      "0": [1, 1, 0],
      "2": [1, 1, 0],
      "4": [1, 1, 0],
      "6": [1, 1, 0],
      "8": [1, 1, 0]
    },
    "152": {
      "0": [1, 0, 0],
      "2": [1, 0, 0],
      "4": [1, 0, 0],
      "6": [1, 0, 0],
      "8": [1, 0, 0]
    },
    "153": {
      "0": [1, 1, 0],
      "2": [1, 1, 0],
      "4": [1, 0, 0],
      "6": [1, 0, 0],
      "8": [1, 0, 0]
    },
    "154": {
      "0": [1, 1, 0],
      "2": [1, 1, 0],
      "4": [1, 1, 0],
      "6": [1, 1, 0],
      "8": [1, 1, 0]
    },
    "155": {
      "0": [1, 0, 0],
      "2": [1, 0, 0],
      "4": [1, 0, 0],
      "6": [1, 0, 0],
      "8": [1, 0, 0]
    },
    "156": {
      "0": [1, 0, 0],
      "2": [1, 0, 0],
      "4": [1, 0, 0],
      "6": [1, 0, 0],
      "8": [1, 0, 0]
    },
    "157": {
      "0": [1, 1, 0],
      "2": [1, 1, 0],
      "4": [1, 0, 0],
      "6": [1, 0, 0],
      "8": [1, 0, 0]
    },
    "158": {
      "0": [1, 1, 0],
      "2": [1, 1, 0],
      "4": [1, 1, 0],
      "6": [1, 1, 0],
      "8": [1, 1, 0]
    },
    "159": {
      "0": [1, 1, 0],
      "2": [1, 1, 0],
      "4": [1, 0, 0],
      "6": [1, 0, 0],
      "8": [1, 0, 0]
    },
    "160": {
      "0": [1, 0, 0],
      "2": [1, 0, 0],
      "4": [1, 0, 0],
      "6": [1, 0, 0],
      "8": [1, 0, 0]
    },
    "161": {
      "0": [1, 0, 0],
      "2": [1, 0, 0],
      "4": [1, 0, 0],
      "6": [1, 0, 0],
      "8": [1, 0, 0]
    },
    "162": {
      "0": [1, 1, 0],
      "2": [1, 1, 0],
      "4": [1, 1, 0],
      "6": [1, 1, 0],
      "8": [1, 1, 0]
    },
    "163": {
      "0": [1, 0, 0],
      "2": [1, 0, 0],
      "4": [1, 0, 0],
      "6": [1, 0, 0],
      "8": [1, 0, 0]
    },
    "165": {
      "0": [1, 0, 0],
      "2": [1, 0, 0],
      "4": [1, 0, 0],
      "6": [1, 0, 0],
      "8": [1, 0, 0]
    },
    "167": {
      "0": [1, 0, 0],
      "2": [1, 0, 0],
      "4": [1, 0, 0],
      "6": [1, 0, 0],
      "8": [1, 0, 0]
    },
    "168": {
      "0": [1, 1, 0],
      "2": [1, 1, 0],
      "4": [1, 1, 0],
      "6": [1, 1, 0],
      "8": [1, 1, 0]
    },
    "169": {
      "0": [1, 1, 0],
      "2": [1, 1, 0],
      "4": [1, 1, 0],
      "6": [1, 1, 0],
      "8": [1, 1, 0]
    },
    "170": {
      "0": [1, 1, 0],
      "2": [1, 1, 0],
      "4": [1, 1, 0],
      "6": [1, 1, 0],
      "8": [1, 1, 0]
    },
    "172": {
      "0": [1, 1, 0],
      "2": [1, 1, 0],
      "4": [1, 1, 0],
      "6": [1, 1, 0],
      "8": [1, 1, 0]
    },
    "174": {
      "0": [1, 1, 0],
      "2": [1, 1, 0],
      "4": [1, 1, 0],
      "6": [1, 1, 0],
      "8": [1, 1, 0]
    },
    "176": {
      "0": [1, 1, 0],
      "2": [1, 1, 0],
      "4": [1, 1, 0],
      "6": [1, 1, 0],
      "8": [1, 1, 0]
    },
    "178": {
      "0": [1, 1, 0],
      "2": [1, 1, 0],
      "4": [1, 1, 0],
      "6": [1, 1, 0],
      "8": [1, 1, 0]
    },
    "180": {
      "0": [1, 1, 0],
      "2": [1, 1, 0],
      "4": [1, 1, 0],
      "6": [1, 1, 0],
      "8": [1, 1, 0]
    },
    "182": {
      "0": [1, 1, 0],
      "2": [1, 1, 0],
      "4": [1, 1, 0],
      "6": [1, 1, 0],
      "8": [1, 1, 0]
    },
    "184": {
      "0": [1, 1, 0],
      "2": [1, 1, 0],
      "4": [1, 1, 0],
      "6": [1, 1, 0],
      "8": [1, 1, 0]
    },
    "186": {
      "0": [1, 0, 0],
      "2": [1, 0, 0],
      "4": [1, 0, 0],
      "6": [1, 0, 0],
      "8": [1, 0, 0]
    },
    "187": {
      "0": [1, 1, 0],
      "2": [1, 1, 0],
      "4": [1, 1, 0],
      "6": [1, 1, 0],
      "8": [1, 1, 0]
    },
    "188": {
      "0": [1, 1, 0],
      "2": [1, 1, 0],
      "4": [1, 1, 0],
      "6": [1, 1, 0],
      "8": [1, 1, 0]
    },
    "190": {
      "0": [1, 1, 0],
      "2": [1, 1, 0],
      "4": [1, 1, 0],
      "6": [1, 1, 0],
      "8": [1, 1, 0]
    },
    "192": {
      "0": [1, 1, 0],
      "2": [1, 1, 0],
      "4": [1, 1, 0],
      "6": [1, 1, 0],
      "8": [1, 1, 0]
    },
    "194": {
      "0": [1, 1, 0],
      "2": [1, 1, 0],
      "4": [1, 1, 0],
      "6": [1, 1, 0],
      "8": [1, 1, 0]
    },
    "196": {
      "0": [1, 0, 0],
      "2": [1, 0, 0],
      "4": [1, 0, 0],
      "6": [1, 0, 0],
      "8": [1, 0, 0]
    },
    "198": {
      "0": [1, 1, 0],
      "2": [1, 1, 0],
      "4": [1, 1, 0],
      "6": [1, 1, 0],
      "8": [1, 1, 0]
    },
    "200": {
      "0": [1, 1, 0],
      "2": [1, 1, 0],
      "4": [1, 1, 0],
      "6": [1, 1, 0],
      "8": [1, 1, 0]
    },
    "201": {
      "0": [1, 1, 0],
      "2": [1, 1, 0],
      "4": [1, 1, 0],
      "6": [1, 1, 0],
      "8": [1, 1, 0]
    },
    "202": {
      "0": [1, 1, 0],
      "2": [1, 1, 0],
      "4": [1, 1, 0],
      "6": [1, 1, 0],
      "8": [1, 1, 0]
    },
    "1A": {
      "0": [1, 1, 0],
      "2": [1, 1, 0],
      "4": [1, 1, 0],
      "6": [1, 1, 0],
      "8": [1, 1, 0]
    },
    "22A": {
      "0": [1, 1, 0],
      "2": [1, 1, 0],
      "4": [1, 1, 0],
      "6": [1, 1, 0],
      "8": [1, 1, 0]
    },
    "24B": {
      "0": [1, 1, 0],
      "2": [1, 1, 0],
      "4": [1, 1, 0],
      "6": [1, 1, 0],
      "8": [1, 1, 0]
    },
    "24C": {
      "0": [1, 1, 0],
      "2": [1, 1, 0],
      "4": [1, 1, 0],
      "6": [1, 1, 0],
      "8": [1, 1, 0]
    },
    "24D": {
      "0": [1, 1, 0],
      "2": [1, 1, 0],
      "4": [1, 1, 0],
      "6": [1, 1, 0],
      "8": [1, 1, 0]
    },
    "25A": {
      "0": [1, 1, 0],
      "2": [1, 1, 0],
      "4": [1, 1, 0],
      "6": [1, 1, 0],
      "8": [1, 1, 0]
    },
    "36A": {
      "0": [1, 1, 0],
      "2": [1, 1, 0],
      "4": [1, 1, 0],
      "6": [1, 1, 0],
      "8": [1, 1, 0]
    },
    "41A": {
      "0": [1, 1, 0],
      "2": [1, 1, 0],
      "4": [1, 1, 0],
      "6": [1, 1, 0],
      "8": [1, 1, 0]
    },
    "42A": {
      "0": [1, 1, 0],
      "2": [1, 1, 0],
      "4": [1, 1, 0],
      "6": [1, 1, 0],
      "8": [1, 1, 0]
    },
    "66A": {
      "0": [1, 1, 0],
      "2": [1, 1, 0],
      "4": [1, 1, 0],
      "6": [1, 1, 0],
      "8": [1, 1, 0]
    },
    "68A": {
      "0": [1, 1, 0],
      "2": [1, 1, 0],
      "4": [1, 1, 0],
      "6": [1, 1, 0],
      "8": [1, 1, 0]
    },
    "68B": {
      "0": [1, 1, 0],
      "2": [1, 1, 0],
      "4": [1, 1, 0],
      "6": [1, 1, 0],
      "8": [1, 1, 0]
    },
    "84A": {
      "0": [1, 1, 0],
      "2": [1, 1, 0],
      "4": [1, 1, 0],
      "6": [1, 1, 0],
      "8": [1, 1, 0]
    },
    "88A": {
      "0": [1, 1, 0],
      "2": [1, 1, 0],
      "4": [1, 1, 0],
      "6": [1, 1, 0],
      "8": [1, 1, 0]
    },
    "92A": {
      "0": [1, 1, 0],
      "2": [1, 1, 0],
      "4": [1, 1, 0],
      "6": [1, 1, 0],
      "8": [1, 1, 0]
    },
    "94A": {
      "0": [1, 1, 0],
      "2": [1, 1, 0],
      "4": [1, 1, 0],
      "6": [1, 1, 0],
      "8": [1, 1, 0]
    },
    "94B": {
      "0": [1, 1, 0],
      "2": [1, 1, 0],
      "4": [1, 1, 0],
      "6": [1, 1, 0],
      "8": [1, 1, 0]
    },
    "96A": {
      "0": [1, 1, 0],
      "2": [1, 1, 0],
      "4": [1, 1, 0],
      "6": [1, 1, 0],
      "8": [1, 1, 0]
    },
    "96B": {
      "0": [1, 1, 0],
      "2": [1, 1, 0],
      "4": [1, 1, 0],
      "6": [1, 1, 0],
      "8": [1, 1, 0]
    },
    "104A": {
      "0": [1, 1, 0],
      "2": [1, 1, 0],
      "4": [1, 0, 0],
      "6": [1, 0, 0],
      "8": [1, 0, 0]
    },
    "106A": {
      "0": [1, 1, 0],
      "2": [1, 1, 0],
      "4": [1, 1, 0],
      "6": [1, 1, 0],
      "8": [1, 1, 0]
    },
    "108A": {
      "0": [1, 1, 0],
      "2": [1, 1, 0],
      "4": [1, 1, 0],
      "6": [1, 1, 0],
      "8": [1, 1, 0]
    },
    "110A": {
      "0": [1, 1, 0],
      "2": [1, 1, 0],
      "4": [1, 1, 0],
      "6": [1, 1, 0],
      "8": [1, 1, 0]
    },
    "124A": {
      "0": [1, 1, 0],
      "2": [1, 1, 0],
      "4": [1, 1, 0],
      "6": [1, 1, 0],
      "8": [1, 1, 0]
    },
    "133A": {
      "0": [1, 1, 0],
      "2": [1, 1, 0],
      "4": [1, 1, 0],
      "6": [1, 1, 0],
      "8": [1, 1, 0]
    },
    "136A": {
      "0": [1, 1, 0],
      "2": [1, 1, 0],
      "4": [1, 1, 0],
      "6": [1, 1, 0],
      "8": [1, 1, 0]
    },
    "141A": {
      "0": [1, 1, 0],
      "2": [1, 1, 0],
      "4": [1, 1, 0],
      "6": [1, 1, 0],
      "8": [1, 1, 0]
    },
    "144A": {
      "0": [1, 1, 0],
      "2": [1, 1, 0],
      "4": [1, 1, 0],
      "6": [1, 1, 0],
      "8": [1, 1, 0]
    },
    "144B": {
      "0": [1, 1, 0],
      "2": [1, 1, 0],
      "4": [1, 1, 0],
      "6": [1, 1, 0],
      "8": [1, 1, 0]
    },
    "145B": {
      "0": [1, 1, 0],
      "2": [1, 1, 0],
      "4": [1, 1, 0],
      "6": [1, 1, 0],
      "8": [1, 1, 0]
    },
    "148A": {
      "0": [1, 1, 0],
      "2": [1, 1, 0],
      "4": [1, 1, 0],
      "6": [1, 1, 0],
      "8": [1, 1, 0]
    },
    "149A": {
      "0": [1, 1, 0],
      "2": [1, 1, 0],
      "4": [1, 1, 0],
      "6": [1, 1, 0],
      "8": [1, 1, 0]
    },
    "151A": {
      "0": [1, 1, 0],
      "2": [1, 1, 0],
      "4": [1, 0, 0],
      "6": [1, 0, 0],
      "8": [1, 0, 0]
    },
    "159B": {
      "0": [1, 1, 0],
      "2": [1, 1, 0],
      "4": [1, 0, 0],
      "6": [1, 0, 0],
      "8": [1, 0, 0]
    },
    "160A": {
      "0": [1, 1, 0],
      "2": [1, 1, 0],
      "4": [1, 1, 0],
      "6": [1, 1, 0],
      "8": [1, 1, 0]
    },
    "178A": {
      "0": [1, 1, 0],
      "2": [1, 1, 0],
      "4": [1, 1, 0],
      "6": [1, 1, 0],
      "8": [1, 1, 0]
    },
    "7A": {
      "0": [1, 0, 0],
      "2": [1, 0, 0],
      "4": [1, 0, 0],
      "6": [1, 0, 0],
      "8": [1, 0, 0]
    },
    "10A": {
      "0": [1, 0, 0],
      "2": [1, 0, 0],
      "4": [1, 0, 0],
      "6": [1, 0, 0],
      "8": [1, 0, 0]
    },
    "12A": {
      "0": [1, 0, 0],
      "2": [1, 0, 0],
      "4": [1, 0, 0],
      "6": [1, 0, 0],
      "8": [1, 0, 0]
    },
    "14A": {
      "0": [1, 0, 0],
      "2": [1, 0, 0],
      "4": [1, 0, 0],
      "6": [1, 0, 0],
      "8": [1, 0, 0]
    },
    "16A": {
      "0": [1, 0, 0],
      "2": [1, 0, 0],
      "4": [1, 0, 0],
      "6": [1, 0, 0],
      "8": [1, 0, 0]
    },
    "19A": {
      "0": [1, 0, 0],
      "2": [1, 0, 0],
      "4": [1, 0, 0],
      "6": [1, 0, 0],
      "8": [1, 0, 0]
    },
    "20A": {
      "0": [1, 0, 0],
      "2": [1, 0, 0],
      "4": [1, 0, 0],
      "6": [1, 0, 0],
      "8": [1, 0, 0]
    },
    "21A": {
      "0": [1, 0, 0],
      "2": [1, 0, 0],
      "4": [1, 0, 0],
      "6": [1, 0, 0],
      "8": [1, 0, 0]
    },
    "23A": {
      "0": [1, 0, 0],
      "2": [1, 0, 0],
      "4": [1, 0, 0],
      "6": [1, 0, 0],
      "8": [1, 0, 0]
    },
    "24A": {
      "0": [1, 0, 0],
      "2": [1, 0, 0],
      "4": [1, 0, 0],
      "6": [1, 0, 0],
      "8": [1, 0, 0]
    },
    "26A": {
      "0": [1, 0, 0],
      "2": [1, 0, 0],
      "4": [1, 0, 0],
      "6": [1, 0, 0],
      "8": [1, 0, 0]
    },
    "32A": {
      "0": [1, 0, 0],
      "2": [1, 0, 0],
      "4": [1, 0, 0],
      "6": [1, 0, 0],
      "8": [1, 0, 0]
    },
    "34A": {
      "0": [1, 0, 0],
      "2": [1, 0, 0],
      "4": [1, 0, 0],
      "6": [1, 0, 0],
      "8": [1, 0, 0]
    },
    "35A": {
      "0": [1, 0, 0],
      "2": [1, 0, 0],
      "4": [1, 0, 0],
      "6": [1, 0, 0],
      "8": [1, 0, 0]
    },
    "36B": {
      "0": [1, 0, 0],
      "2": [1, 0, 0],
      "4": [1, 0, 0],
      "6": [1, 0, 0],
      "8": [1, 0, 0]
    },
    "37A": {
      "0": [1, 0, 0],
      "2": [1, 0, 0],
      "4": [1, 0, 0],
      "6": [1, 0, 0],
      "8": [1, 0, 0]
    },
    "40A": {
      "0": [1, 0, 0],
      "2": [1, 0, 0],
      "4": [1, 0, 0],
      "6": [1, 0, 0],
      "8": [1, 0, 0]
    },
    "42B": {
      "0": [1, 0, 0],
      "2": [1, 0, 0],
      "4": [1, 0, 0],
      "6": [1, 0, 0],
      "8": [1, 0, 0]
    },
    "43A": {
      "0": [1, 0, 0],
      "2": [1, 0, 0],
      "4": [1, 0, 0],
      "6": [1, 0, 0],
      "8": [1, 0, 0]
    },
    "43B": {
      "0": [1, 0, 0],
      "2": [1, 0, 0],
      "4": [1, 0, 0],
      "6": [1, 0, 0],
      "8": [1, 0, 0]
    },
    "43C": {
      "0": [1, 0, 0],
      "2": [1, 0, 0],
      "4": [1, 0, 0],
      "6": [1, 0, 0],
      "8": [1, 0, 0]
    },
    "44A": {
      "0": [1, 0, 0],
      "2": [1, 0, 0],
      "4": [1, 0, 0],
      "6": [1, 0, 0],
      "8": [1, 0, 0]
    },
    "44B": {
      "0": [1, 0, 0],
      "2": [1, 0, 0],
      "4": [1, 0, 0],
      "6": [1, 0, 0],
      "8": [1, 0, 0]
    },
    "45A": {
      "0": [1, 0, 0],
      "2": [1, 0, 0],
      "4": [1, 0, 0],
      "6": [1, 0, 0],
      "8": [1, 0, 0]
    },
    "46A": {
      "0": [1, 0, 0],
      "2": [1, 0, 0],
      "4": [1, 0, 0],
      "6": [1, 0, 0],
      "8": [1, 0, 0]
    },
    "47A": {
      "0": [1, 0, 0],
      "2": [1, 0, 0],
      "4": [1, 0, 0],
      "6": [1, 0, 0],
      "8": [1, 0, 0]
    },
    "49A": {
      "0": [1, 0, 0],
      "2": [1, 0, 0],
      "4": [1, 0, 0],
      "6": [1, 0, 0],
      "8": [1, 0, 0]
    },
    "53A": {
      "0": [1, 0, 0],
      "2": [1, 0, 0],
      "4": [1, 0, 0],
      "6": [1, 0, 0],
      "8": [1, 0, 0]
    },
    "62A": {
      "0": [1, 0, 0],
      "2": [1, 0, 0],
      "4": [1, 0, 0],
      "6": [1, 0, 0],
      "8": [1, 0, 0]
    },
    "70A": {
      "0": [1, 0, 0],
      "2": [1, 0, 0],
      "4": [1, 0, 0],
      "6": [1, 0, 0],
      "8": [1, 0, 0]
    },
    "72A": {
      "0": [1, 0, 0],
      "2": [1, 0, 0],
      "4": [1, 0, 0],
      "6": [1, 0, 0],
      "8": [1, 0, 0]
    },
    "74B": {
      "0": [1, 0, 0],
      "2": [1, 0, 0],
      "4": [1, 0, 0],
      "6": [1, 0, 0],
      "8": [1, 0, 0]
    },
    "76A": {
      "0": [1, 0, 0],
      "2": [1, 0, 0],
      "4": [1, 0, 0],
      "6": [1, 0, 0],
      "8": [1, 0, 0]
    },
    "82A": {
      "0": [1, 0, 0],
      "2": [1, 0, 0],
      "4": [1, 0, 0],
      "6": [1, 0, 0],
      "8": [1, 0, 0]
    },
    "92B": {
      "0": [1, 0, 0],
      "2": [1, 0, 0],
      "4": [1, 1, 0],
      "6": [1, 1, 0],
      "8": [1, 1, 0]
    },
    "92C": {
      "0": [1, 0, 0],
      "2": [1, 0, 0],
      "4": [1, 0, 0],
      "6": [1, 0, 0],
      "8": [1, 0, 0]
    },
    "92D": {
      "0": [1, 0, 0],
      "2": [1, 0, 0],
      "4": [1, 0, 0],
      "6": [1, 0, 0],
      "8": [1, 0, 0]
    },
    "100A": {
      "0": [1, 0, 0],
      "2": [1, 0, 0],
      "4": [1, 0, 0],
      "6": [1, 0, 0],
      "8": [1, 0, 0]
    },
    "102A": {
      "0": [1, 0, 0],
      "2": [1, 0, 0],
      "4": [1, 0, 0],
      "6": [1, 0, 0],
      "8": [1, 0, 0]
    },
    "102B": {
      "0": [1, 0, 0],
      "2": [1, 0, 0],
      "4": [1, 0, 0],
      "6": [1, 0, 0],
      "8": [1, 0, 0]
    },
    "108B": { "2": [1, 1, 0], "4": [1, 1, 0], "6": [1, 1, 0], "8": [1, 1, 0] },
    "120A": {
      "0": [1, 0, 0],
      "2": [1, 0, 0],
      "4": [1, 0, 0],
      "6": [1, 0, 0],
      "8": [1, 0, 0]
    },
    "121A": {
      "0": [1, 0, 0],
      "2": [1, 0, 0],
      "4": [1, 0, 0],
      "6": [1, 0, 0],
      "8": [1, 0, 0]
    },
    "121B": {
      "0": [1, 0, 0],
      "2": [1, 0, 0],
      "4": [1, 0, 0],
      "6": [1, 0, 0],
      "8": [1, 0, 0]
    },
    "121C": {
      "0": [1, 0, 0],
      "2": [1, 0, 0],
      "4": [1, 0, 0],
      "6": [1, 0, 0],
      "8": [1, 0, 0]
    },
    "121D": {
      "0": [1, 0, 0],
      "2": [1, 0, 0],
      "4": [1, 0, 0],
      "6": [1, 0, 0],
      "8": [1, 0, 0]
    },
    "121E": {
      "0": [1, 0, 0],
      "2": [1, 0, 0],
      "4": [1, 0, 0],
      "6": [1, 0, 0],
      "8": [1, 0, 0]
    },
    "121F": {
      "0": [1, 0, 0],
      "2": [1, 0, 0],
      "4": [1, 0, 0],
      "6": [1, 0, 0],
      "8": [1, 0, 0]
    },
    "122A": {
      "0": [1, 0, 0],
      "2": [1, 0, 0],
      "4": [1, 0, 0],
      "6": [1, 0, 0],
      "8": [1, 0, 0]
    },
    "122B": {
      "0": [1, 0, 0],
      "2": [1, 0, 0],
      "4": [1, 0, 0],
      "6": [1, 0, 0],
      "8": [1, 0, 0]
    },
    "131A": {
      "0": [1, 0, 0],
      "2": [1, 0, 0],
      "4": [1, 0, 0],
      "6": [1, 0, 0],
      "8": [1, 0, 0]
    },
    "132A": {
      "0": [1, 0, 0],
      "2": [1, 0, 0],
      "4": [1, 0, 0],
      "6": [1, 0, 0],
      "8": [1, 0, 0]
    },
    "134A": {
      "0": [1, 0, 0],
      "2": [1, 0, 0],
      "4": [1, 0, 0],
      "6": [1, 0, 0],
      "8": [1, 0, 0]
    },
    "134B": {
      "0": [1, 0, 0],
      "2": [1, 0, 0],
      "4": [1, 0, 0],
      "6": [1, 0, 0],
      "8": [1, 0, 0]
    },
    "135A": {
      "0": [1, 0, 0],
      "2": [1, 0, 0],
      "4": [1, 0, 0],
      "6": [1, 0, 0],
      "8": [1, 0, 0]
    },
    "139A": {
      "0": [1, 0, 0],
      "2": [1, 0, 0],
      "4": [1, 0, 0],
      "6": [1, 0, 0],
      "8": [1, 0, 0]
    },
    "145A": {
      "0": [1, 0, 0],
      "2": [1, 0, 0],
      "4": [1, 0, 0],
      "6": [1, 0, 0],
      "8": [1, 0, 0]
    },
    "153A": {
      "0": [1, 0, 0],
      "2": [1, 0, 0],
      "4": [1, 0, 0],
      "6": [1, 0, 0],
      "8": [1, 0, 0]
    },
    "154A": {
      "0": [1, 0, 0],
      "2": [1, 0, 0],
      "4": [1, 0, 0],
      "6": [1, 0, 0],
      "8": [1, 0, 0]
    },
    "155A": {
      "0": [1, 0, 0],
      "2": [1, 0, 0],
      "4": [1, 0, 0],
      "6": [1, 0, 0],
      "8": [1, 0, 0]
    },
    "156A": {
      "0": [1, 0, 0],
      "2": [1, 0, 0],
      "4": [1, 0, 0],
      "6": [1, 0, 0],
      "8": [1, 0, 0]
    },
    "159A": {
      "0": [1, 0, 0],
      "2": [1, 0, 0],
      "4": [1, 0, 0],
      "6": [1, 0, 0],
      "8": [1, 0, 0]
    },
    "159C": {
      "0": [1, 0, 0],
      "2": [1, 0, 0],
      "4": [1, 0, 0],
      "6": [1, 0, 0],
      "8": [1, 0, 0]
    },
    "159D": {
      "0": [1, 0, 0],
      "2": [1, 0, 0],
      "4": [1, 0, 0],
      "6": [1, 0, 0],
      "8": [1, 0, 0]
    },
    "162A": {
      "0": [1, 0, 0],
      "2": [1, 0, 0],
      "4": [1, 0, 0],
      "6": [1, 0, 0],
      "8": [1, 0, 0]
    },
    "168A": {
      "0": [1, 0, 0],
      "2": [1, 0, 0],
      "4": [1, 0, 0],
      "6": [1, 0, 0],
      "8": [1, 0, 0]
    },
    "176A": {
      "0": [1, 0, 0],
      "2": [1, 0, 0],
      "4": [1, 0, 0],
      "6": [1, 0, 0],
      "8": [1, 0, 0]
    },
    "178B": {
      "0": [1, 0, 0],
      "2": [1, 0, 0],
      "4": [1, 0, 0],
      "6": [1, 0, 0],
      "8": [1, 0, 0]
    },
    "184A": {
      "0": [1, 0, 0],
      "2": [1, 0, 0],
      "4": [1, 0, 0],
      "6": [1, 0, 0],
      "8": [1, 0, 0]
    },
    "184B": {
      "0": [1, 0, 0],
      "2": [1, 0, 0],
      "4": [1, 0, 0],
      "6": [1, 0, 0],
      "8": [1, 0, 0]
    },
    "184C": {
      "0": [1, 0, 0],
      "2": [1, 0, 0],
      "4": [1, 0, 0],
      "6": [1, 0, 0],
      "8": [1, 0, 0]
    },
    "188A": {
      "0": [1, 0, 0],
      "2": [1, 0, 0],
      "4": [1, 0, 0],
      "6": [1, 0, 0],
      "8": [1, 0, 0]
    },
    "192A": {
      "0": [1, 0, 0],
      "2": [1, 0, 0],
      "4": [1, 0, 0],
      "6": [1, 0, 0],
      "8": [1, 0, 0]
    },
    "196A": {
      "0": [1, 0, 0],
      "2": [1, 0, 0],
      "4": [1, 0, 0],
      "6": [1, 0, 0],
      "8": [1, 0, 0]
    },
    "78A": { "4": [1, 1, 0], "6": [1, 1, 0], "8": [1, 1, 0] }
  }
}
