{
  "12437": {
    "5": {
      "0": [0, 0, 1],
      "2": [0, 0, 1],
      "4": [1, 0, 1],
      "6": [1, 0, 1],
      "8": [1, 0, 1]
    },
    "7": {
      "0": [0, 0, 1],
      "2": [0, 0, 1],
      "4": [1, 0, 1],
      "6": [1, 0, 1],
      "8": [1, 0, 1]
    },
    "9": {
      "0": [0, 0, 1],
      "2": [0, 0, 1],
      "4": [1, 0, 1],
      "6": [1, 0, 1],
      "8": [1, 0, 1]
    },
    "11": {
      "0": [0, 0, 1],
      "2": [0, 0, 1],
      "4": [1, 0, 1],
      "6": [1, 0, 1],
      "8": [1, 0, 1]
    },
    "13": {
      "0": [0, 0, 1],
      "2": [0, 0, 1],
      "4": [1, 0, 1],
      "6": [1, 0, 1],
      "8": [1, 0, 1]
    },
    "15": {
      "0": [0, 0, 1],
      "2": [0, 0, 1],
      "4": [1, 0, 1],
      "6": [1, 0, 1],
      "8": [1, 0, 1]
    },
    "17": {
      "0": [0, 0, 1],
      "2": [0, 0, 1],
      "4": [1, 0, 1],
      "6": [1, 0, 1],
      "8": [1, 0, 1]
    },
    "19": {
      "0": [0, 0, 1],
      "2": [0, 0, 1],
      "4": [1, 0, 1],
      "6": [1, 0, 1],
      "8": [1, 0, 1]
    },
    "31": {
      "0": [0, 0, 1],
      "2": [0, 0, 1],
      "4": [1, 0, 1],
      "6": [1, 0, 1],
      "8": [1, 0, 1]
    },
    "33": {
      "0": [0, 0, 1],
      "2": [0, 0, 1],
      "4": [1, 0, 1],
      "6": [1, 0, 1],
      "8": [1, 0, 1]
    },
    "35": {
      "0": [0, 0, 1],
      "2": [0, 0, 1],
      "4": [1, 0, 1],
      "6": [1, 0, 1],
      "8": [1, 0, 1]
    },
    "37": {
      "0": [0, 0, 1],
      "2": [0, 0, 1],
      "4": [1, 0, 1],
      "6": [1, 0, 1],
      "8": [1, 0, 1]
    },
    "39": {
      "0": [0, 0, 1],
      "2": [0, 0, 1],
      "4": [1, 0, 1],
      "6": [1, 0, 1],
      "8": [1, 0, 1]
    },
    "41": {
      "0": [0, 0, 1],
      "2": [0, 0, 1],
      "4": [1, 0, 1],
      "6": [1, 0, 1],
      "8": [1, 0, 1]
    },
    "43": {
      "0": [0, 0, 1],
      "2": [0, 0, 1],
      "4": [1, 0, 1],
      "6": [1, 0, 1],
      "8": [1, 0, 1]
    },
    "45": {
      "0": [0, 0, 1],
      "2": [0, 0, 1],
      "4": [1, 0, 1],
      "6": [1, 0, 1],
      "8": [1, 0, 1]
    },
    "50": {
      "0": [0, 0, 1],
      "2": [0, 0, 1],
      "4": [0, 0, 1],
      "6": [0, 0, 1],
      "8": [0, 0, 1]
    },
    "51": {
      "0": [0, 0, 1],
      "2": [0, 0, 1],
      "4": [0, 0, 1],
      "6": [0, 0, 1],
      "8": [0, 0, 1]
    },
    "52": {
      "0": [0, 0, 1],
      "2": [0, 0, 1],
      "4": [0, 0, 1],
      "6": [0, 0, 1],
      "8": [0, 0, 1]
    },
    "54": {
      "0": [0, 0, 1],
      "2": [0, 0, 1],
      "4": [0, 0, 1],
      "6": [0, 0, 1],
      "8": [0, 0, 1]
    },
    "56": {
      "0": [0, 0, 1],
      "2": [0, 0, 1],
      "4": [0, 0, 1],
      "6": [0, 0, 1],
      "8": [0, 0, 1]
    },
    "57": {
      "0": [0, 0, 1],
      "2": [0, 0, 1],
      "4": [0, 0, 1],
      "6": [0, 0, 1],
      "8": [0, 0, 1]
    },
    "58": {
      "0": [0, 0, 1],
      "2": [0, 0, 1],
      "4": [0, 0, 1],
      "6": [0, 0, 1],
      "8": [0, 0, 1]
    },
    "59": {
      "0": [0, 0, 1],
      "2": [0, 0, 1],
      "4": [0, 0, 1],
      "6": [0, 0, 1],
      "8": [0, 0, 1]
    },
    "60": {
      "0": [0, 0, 1],
      "2": [0, 0, 1],
      "4": [0, 0, 1],
      "6": [0, 0, 1],
      "8": [0, 0, 1]
    },
    "64": {
      "0": [0, 0, 1],
      "2": [0, 0, 1],
      "4": [0, 0, 1],
      "6": [0, 0, 1],
      "8": [0, 0, 1]
    },
    "65": {
      "0": [0, 0, 1],
      "2": [0, 0, 1],
      "4": [0, 0, 1],
      "6": [0, 0, 1],
      "8": [0, 0, 1]
    },
    "66": {
      "0": [0, 0, 1],
      "2": [0, 0, 1],
      "4": [0, 0, 1],
      "6": [0, 0, 1],
      "8": [0, 0, 1]
    },
    "67": {
      "0": [0, 0, 1],
      "2": [0, 0, 1],
      "4": [0, 0, 1],
      "6": [0, 0, 1],
      "8": [0, 0, 1]
    },
    "68": {
      "0": [0, 0, 1],
      "2": [0, 0, 1],
      "4": [0, 0, 1],
      "6": [0, 0, 1],
      "8": [0, 0, 1]
    },
    "69": {
      "0": [0, 0, 1],
      "2": [0, 0, 1],
      "4": [0, 0, 1],
      "6": [0, 0, 1],
      "8": [0, 0, 1]
    },
    "70": {
      "0": [0, 0, 1],
      "2": [0, 0, 1],
      "4": [0, 0, 1],
      "6": [0, 0, 1],
      "8": [0, 0, 1]
    },
    "71": {
      "0": [0, 0, 1],
      "2": [0, 0, 1],
      "4": [0, 0, 1],
      "6": [0, 0, 1],
      "8": [0, 0, 1]
    },
    "74": {
      "0": [0, 0, 1],
      "2": [0, 0, 1],
      "4": [0, 0, 1],
      "6": [0, 0, 1],
      "8": [0, 0, 1]
    },
    "75": {
      "0": [0, 0, 1],
      "2": [0, 0, 1],
      "4": [0, 0, 1],
      "6": [0, 0, 1],
      "8": [0, 0, 1]
    },
    "76": {
      "0": [0, 0, 1],
      "2": [0, 0, 1],
      "4": [0, 0, 1],
      "6": [0, 0, 1],
      "8": [0, 0, 1]
    },
    "77": {
      "0": [0, 0, 1],
      "2": [0, 0, 1],
      "4": [0, 0, 1],
      "6": [0, 0, 1],
      "8": [0, 0, 1]
    },
    "78": {
      "0": [0, 0, 1],
      "2": [0, 0, 1],
      "4": [0, 0, 1],
      "6": [0, 0, 1],
      "8": [0, 0, 1]
    },
    "79": {
      "0": [0, 0, 1],
      "2": [0, 0, 1],
      "4": [0, 0, 1],
      "6": [0, 0, 1],
      "8": [0, 0, 1]
    },
    "80": {
      "0": [0, 0, 1],
      "2": [0, 0, 1],
      "4": [0, 0, 1],
      "6": [0, 0, 1],
      "8": [0, 0, 1]
    },
    "82": {
      "0": [0, 0, 1],
      "2": [0, 0, 1],
      "4": [0, 0, 1],
      "6": [0, 0, 1],
      "8": [0, 0, 1]
    },
    "83": {
      "0": [0, 0, 1],
      "2": [0, 0, 1],
      "4": [0, 0, 1],
      "6": [0, 0, 1],
      "8": [0, 0, 1]
    },
    "85": {
      "0": [0, 0, 1],
      "2": [0, 0, 1],
      "4": [0, 0, 1],
      "6": [0, 0, 1],
      "8": [0, 0, 1]
    },
    "86": {
      "0": [0, 0, 1],
      "2": [0, 0, 1],
      "4": [0, 0, 1],
      "6": [0, 0, 1],
      "8": [0, 0, 1]
    },
    "87": {
      "0": [0, 0, 1],
      "2": [0, 0, 1],
      "4": [0, 0, 1],
      "6": [0, 0, 1],
      "8": [0, 0, 1]
    },
    "88": {
      "0": [0, 0, 1],
      "2": [0, 0, 1],
      "4": [0, 0, 1],
      "6": [0, 0, 1],
      "8": [0, 0, 1]
    },
    "89": {
      "0": [0, 1, 1],
      "2": [0, 1, 1],
      "4": [0, 1, 1],
      "6": [0, 1, 1],
      "8": [0, 1, 1]
    },
    "90": {
      "0": [0, 0, 1],
      "2": [0, 0, 1],
      "4": [0, 0, 1],
      "6": [0, 0, 1],
      "8": [0, 0, 1]
    },
    "91": {
      "0": [0, 1, 1],
      "2": [0, 1, 1],
      "4": [0, 1, 1],
      "6": [0, 1, 1],
      "8": [0, 1, 1]
    },
    "92": {
      "0": [0, 1, 1],
      "2": [0, 1, 1],
      "4": [0, 1, 1],
      "6": [0, 1, 1],
      "8": [0, 1, 1]
    },
    "8A": {
      "0": [0, 0, 1],
      "2": [0, 0, 1],
      "4": [1, 0, 1],
      "6": [1, 0, 1],
      "8": [1, 0, 1]
    },
    "8B": {
      "0": [0, 0, 1],
      "2": [0, 0, 1],
      "4": [1, 0, 1],
      "6": [1, 0, 1],
      "8": [1, 0, 1]
    },
    "8C": {
      "0": [0, 0, 1],
      "2": [0, 0, 1],
      "4": [1, 0, 1],
      "6": [1, 0, 1],
      "8": [1, 0, 1]
    },
    "8D": {
      "0": [0, 0, 1],
      "2": [0, 0, 1],
      "4": [1, 0, 1],
      "6": [1, 0, 1],
      "8": [1, 0, 1]
    },
    "8E": {
      "0": [0, 0, 1],
      "2": [0, 0, 1],
      "4": [1, 0, 1],
      "6": [1, 0, 1],
      "8": [1, 0, 1]
    },
    "8F": {
      "0": [0, 0, 1],
      "2": [0, 0, 1],
      "4": [1, 0, 1],
      "6": [1, 0, 1],
      "8": [1, 0, 1]
    },
    "10A": {
      "0": [0, 0, 1],
      "2": [0, 0, 1],
      "4": [1, 0, 1],
      "6": [1, 0, 1],
      "8": [1, 0, 1]
    },
    "10B": {
      "0": [0, 0, 1],
      "2": [0, 0, 1],
      "4": [1, 0, 1],
      "6": [1, 0, 1],
      "8": [1, 0, 1]
    },
    "10C": {
      "0": [0, 0, 1],
      "2": [0, 0, 1],
      "4": [1, 0, 1],
      "6": [1, 0, 1],
      "8": [1, 0, 1]
    },
    "10D": {
      "0": [0, 0, 1],
      "2": [0, 0, 1],
      "4": [1, 0, 1],
      "6": [1, 0, 1],
      "8": [1, 0, 1]
    },
    "10E": {
      "0": [0, 0, 1],
      "2": [0, 0, 1],
      "4": [1, 0, 1],
      "6": [1, 0, 1],
      "8": [1, 0, 1]
    },
    "10F": {
      "0": [0, 0, 1],
      "2": [0, 0, 1],
      "4": [1, 0, 1],
      "6": [1, 0, 1],
      "8": [1, 0, 1]
    },
    "12A": {
      "0": [0, 0, 1],
      "2": [0, 0, 1],
      "4": [1, 0, 1],
      "6": [1, 0, 1],
      "8": [1, 0, 1]
    },
    "12B": {
      "0": [0, 0, 1],
      "2": [0, 0, 1],
      "4": [1, 0, 1],
      "6": [1, 0, 1],
      "8": [1, 0, 1]
    },
    "12C": {
      "0": [0, 0, 1],
      "2": [0, 0, 1],
      "4": [1, 0, 1],
      "6": [1, 0, 1],
      "8": [1, 0, 1]
    },
    "12D": {
      "0": [0, 0, 1],
      "2": [0, 0, 1],
      "4": [1, 0, 1],
      "6": [1, 0, 1],
      "8": [1, 0, 1]
    },
    "12E": {
      "0": [0, 0, 1],
      "2": [0, 0, 1],
      "4": [1, 0, 1],
      "6": [1, 0, 1],
      "8": [1, 0, 1]
    },
    "12F": {
      "0": [0, 0, 1],
      "2": [0, 0, 1],
      "4": [1, 0, 1],
      "6": [1, 0, 1],
      "8": [1, 0, 1]
    },
    "14A": {
      "0": [0, 0, 1],
      "2": [0, 0, 1],
      "4": [1, 0, 1],
      "6": [1, 0, 1],
      "8": [1, 0, 1]
    },
    "14B": {
      "0": [0, 0, 1],
      "2": [0, 0, 1],
      "4": [1, 0, 1],
      "6": [1, 0, 1],
      "8": [1, 0, 1]
    },
    "14C": {
      "0": [0, 0, 1],
      "2": [0, 0, 1],
      "4": [1, 0, 1],
      "6": [1, 0, 1],
      "8": [1, 0, 1]
    },
    "14D": {
      "0": [0, 0, 1],
      "2": [0, 0, 1],
      "4": [1, 0, 1],
      "6": [1, 0, 1],
      "8": [1, 0, 1]
    },
    "14E": {
      "0": [0, 0, 1],
      "2": [0, 0, 1],
      "4": [1, 0, 1],
      "6": [1, 0, 1],
      "8": [1, 0, 1]
    },
    "14F": {
      "0": [0, 0, 1],
      "2": [0, 0, 1],
      "4": [1, 0, 1],
      "6": [1, 0, 1],
      "8": [1, 0, 1]
    },
    "14G": {
      "0": [0, 0, 1],
      "2": [0, 0, 1],
      "4": [1, 0, 1],
      "6": [1, 0, 1],
      "8": [1, 0, 1]
    },
    "14H": {
      "0": [0, 0, 1],
      "2": [0, 0, 1],
      "4": [1, 0, 1],
      "6": [1, 0, 1],
      "8": [1, 0, 1]
    },
    "14I": {
      "0": [0, 0, 1],
      "2": [0, 0, 1],
      "4": [1, 0, 1],
      "6": [1, 0, 1],
      "8": [1, 0, 1]
    },
    "14K": {
      "0": [0, 0, 1],
      "2": [0, 0, 1],
      "4": [1, 0, 1],
      "6": [1, 0, 1],
      "8": [1, 0, 1]
    },
    "16A": {
      "0": [0, 0, 1],
      "2": [0, 0, 1],
      "4": [1, 0, 1],
      "6": [1, 0, 1],
      "8": [1, 0, 1]
    },
    "16B": {
      "0": [0, 0, 1],
      "2": [0, 0, 1],
      "4": [1, 0, 1],
      "6": [1, 0, 1],
      "8": [1, 0, 1]
    },
    "16C": {
      "0": [0, 0, 1],
      "2": [0, 0, 1],
      "4": [1, 0, 1],
      "6": [1, 0, 1],
      "8": [1, 0, 1]
    },
    "16D": {
      "0": [0, 0, 1],
      "2": [0, 0, 1],
      "4": [1, 0, 1],
      "6": [1, 0, 1],
      "8": [1, 0, 1]
    },
    "16E": {
      "0": [0, 0, 1],
      "2": [0, 0, 1],
      "4": [1, 0, 1],
      "6": [1, 0, 1],
      "8": [1, 0, 1]
    },
    "16F": {
      "0": [0, 0, 1],
      "2": [0, 0, 1],
      "4": [1, 0, 1],
      "6": [1, 0, 1],
      "8": [1, 0, 1]
    },
    "16G": {
      "0": [0, 0, 1],
      "2": [0, 0, 1],
      "4": [1, 0, 1],
      "6": [1, 0, 1],
      "8": [1, 0, 1]
    },
    "18A": {
      "0": [0, 0, 1],
      "2": [0, 0, 1],
      "4": [1, 0, 1],
      "6": [1, 0, 1],
      "8": [1, 0, 1]
    },
    "18B": {
      "0": [0, 0, 1],
      "2": [0, 0, 1],
      "4": [1, 0, 1],
      "6": [1, 0, 1],
      "8": [1, 0, 1]
    },
    "18C": {
      "0": [0, 0, 1],
      "2": [0, 0, 1],
      "4": [1, 0, 1],
      "6": [1, 0, 1],
      "8": [1, 0, 1]
    },
    "18D": {
      "0": [0, 0, 1],
      "2": [0, 0, 1],
      "4": [1, 0, 1],
      "6": [1, 0, 1],
      "8": [1, 0, 1]
    },
    "18E": {
      "0": [0, 0, 1],
      "2": [0, 0, 1],
      "4": [1, 0, 1],
      "6": [1, 0, 1],
      "8": [1, 0, 1]
    },
    "18F": {
      "0": [0, 0, 1],
      "2": [0, 0, 1],
      "4": [1, 0, 1],
      "6": [1, 0, 1],
      "8": [1, 0, 1]
    },
    "20A": {
      "0": [0, 0, 1],
      "2": [0, 0, 1],
      "4": [1, 0, 1],
      "6": [1, 0, 1],
      "8": [1, 0, 1]
    },
    "20B": {
      "0": [0, 0, 1],
      "2": [0, 0, 1],
      "4": [1, 0, 1],
      "6": [1, 0, 1],
      "8": [1, 0, 1]
    },
    "20C": {
      "0": [0, 0, 1],
      "2": [0, 0, 1],
      "4": [1, 0, 1],
      "6": [1, 0, 1],
      "8": [1, 0, 1]
    },
    "20D": {
      "0": [0, 0, 1],
      "2": [0, 0, 1],
      "4": [1, 0, 1],
      "6": [1, 0, 1],
      "8": [1, 0, 1]
    },
    "20E": {
      "0": [0, 0, 1],
      "2": [0, 0, 1],
      "4": [1, 0, 1],
      "6": [1, 0, 1],
      "8": [1, 0, 1]
    },
    "20F": {
      "0": [0, 0, 1],
      "2": [0, 0, 1],
      "4": [1, 0, 1],
      "6": [1, 0, 1],
      "8": [1, 0, 1]
    },
    "21A": {
      "0": [0, 0, 1],
      "2": [0, 0, 1],
      "4": [1, 0, 1],
      "6": [1, 0, 1],
      "8": [1, 0, 1]
    },
    "21B": {
      "0": [0, 0, 1],
      "2": [0, 0, 1],
      "4": [1, 0, 1],
      "6": [1, 0, 1],
      "8": [1, 0, 1]
    },
    "22A": {
      "0": [0, 0, 1],
      "2": [0, 0, 1],
      "4": [1, 0, 1],
      "6": [1, 0, 1],
      "8": [1, 0, 1]
    },
    "22B": {
      "0": [0, 0, 1],
      "2": [0, 0, 1],
      "4": [1, 0, 1],
      "6": [1, 0, 1],
      "8": [1, 0, 1]
    },
    "22C": {
      "0": [0, 0, 1],
      "2": [0, 0, 1],
      "4": [1, 0, 1],
      "6": [1, 0, 1],
      "8": [1, 0, 1]
    },
    "22D": {
      "0": [0, 0, 1],
      "2": [0, 0, 1],
      "4": [1, 0, 1],
      "6": [1, 0, 1],
      "8": [1, 0, 1]
    },
    "22E": {
      "0": [0, 0, 1],
      "2": [0, 0, 1],
      "4": [1, 0, 1],
      "6": [1, 0, 1],
      "8": [1, 0, 1]
    },
    "22F": {
      "0": [0, 0, 1],
      "2": [0, 0, 1],
      "4": [1, 0, 1],
      "6": [1, 0, 1],
      "8": [1, 0, 1]
    },
    "23A": {
      "0": [0, 0, 1],
      "2": [0, 0, 1],
      "4": [1, 0, 1],
      "6": [1, 0, 1],
      "8": [1, 0, 1]
    },
    "23B": {
      "0": [0, 0, 1],
      "2": [0, 0, 1],
      "4": [1, 0, 1],
      "6": [1, 0, 1],
      "8": [1, 0, 1]
    },
    "24A": {
      "0": [0, 0, 1],
      "2": [0, 0, 1],
      "4": [1, 0, 1],
      "6": [1, 0, 1],
      "8": [1, 0, 1]
    },
    "24B": {
      "0": [0, 0, 1],
      "2": [0, 0, 1],
      "4": [1, 0, 1],
      "6": [1, 0, 1],
      "8": [1, 0, 1]
    },
    "24C": {
      "0": [0, 0, 1],
      "2": [0, 0, 1],
      "4": [1, 0, 1],
      "6": [1, 0, 1],
      "8": [1, 0, 1]
    },
    "24D": {
      "0": [0, 0, 1],
      "2": [0, 0, 1],
      "4": [1, 0, 1],
      "6": [1, 0, 1],
      "8": [1, 0, 1]
    },
    "24E": {
      "0": [0, 0, 1],
      "2": [0, 0, 1],
      "4": [1, 0, 1],
      "6": [1, 0, 1],
      "8": [1, 0, 1]
    },
    "24F": {
      "0": [0, 0, 1],
      "2": [0, 0, 1],
      "4": [1, 0, 1],
      "6": [1, 0, 1],
      "8": [1, 0, 1]
    },
    "24G": {
      "0": [0, 0, 1],
      "2": [0, 0, 1],
      "4": [1, 0, 1],
      "6": [1, 0, 1],
      "8": [1, 0, 1]
    },
    "24H": {
      "0": [0, 0, 1],
      "2": [0, 0, 1],
      "4": [1, 0, 1],
      "6": [1, 0, 1],
      "8": [1, 0, 1]
    },
    "24I": {
      "0": [0, 0, 1],
      "2": [0, 0, 1],
      "4": [1, 0, 1],
      "6": [1, 0, 1],
      "8": [1, 0, 1]
    },
    "24K": {
      "0": [0, 0, 1],
      "2": [0, 0, 1],
      "4": [1, 0, 1],
      "6": [1, 0, 1],
      "8": [1, 0, 1]
    },
    "25A": {
      "0": [0, 0, 1],
      "2": [0, 0, 1],
      "4": [1, 0, 1],
      "6": [1, 0, 1],
      "8": [1, 0, 1]
    },
    "25B": {
      "0": [0, 0, 1],
      "2": [0, 0, 1],
      "4": [1, 0, 1],
      "6": [1, 0, 1],
      "8": [1, 0, 1]
    },
    "26A": {
      "0": [0, 0, 1],
      "2": [0, 0, 1],
      "4": [1, 0, 1],
      "6": [1, 0, 1],
      "8": [1, 0, 1]
    },
    "26B": {
      "0": [0, 0, 1],
      "2": [0, 0, 1],
      "4": [1, 0, 1],
      "6": [1, 0, 1],
      "8": [1, 0, 1]
    },
    "26C": {
      "0": [0, 0, 1],
      "2": [0, 0, 1],
      "4": [1, 0, 1],
      "6": [1, 0, 1],
      "8": [1, 0, 1]
    },
    "26D": {
      "0": [0, 0, 1],
      "2": [0, 0, 1],
      "4": [1, 0, 1],
      "6": [1, 0, 1],
      "8": [1, 0, 1]
    },
    "26E": {
      "0": [0, 0, 1],
      "2": [0, 0, 1],
      "4": [1, 0, 1],
      "6": [1, 0, 1],
      "8": [1, 0, 1]
    },
    "26F": {
      "0": [0, 0, 1],
      "2": [0, 0, 1],
      "4": [1, 0, 1],
      "6": [1, 0, 1],
      "8": [1, 0, 1]
    },
    "26G": {
      "0": [0, 0, 1],
      "2": [0, 0, 1],
      "4": [1, 0, 1],
      "6": [1, 0, 1],
      "8": [1, 0, 1]
    },
    "27A": {
      "0": [0, 0, 1],
      "2": [0, 0, 1],
      "4": [1, 0, 1],
      "6": [1, 0, 1],
      "8": [1, 0, 1]
    },
    "27B": {
      "0": [0, 0, 1],
      "2": [0, 0, 1],
      "4": [1, 0, 1],
      "6": [1, 0, 1],
      "8": [1, 0, 1]
    },
    "28A": {
      "0": [0, 0, 1],
      "2": [0, 0, 1],
      "4": [1, 0, 1],
      "6": [1, 0, 1],
      "8": [1, 0, 1]
    },
    "28B": {
      "0": [0, 0, 1],
      "2": [0, 0, 1],
      "4": [1, 0, 1],
      "6": [1, 0, 1],
      "8": [1, 0, 1]
    },
    "28C": {
      "0": [0, 0, 1],
      "2": [0, 0, 1],
      "4": [1, 0, 1],
      "6": [1, 0, 1],
      "8": [1, 0, 1]
    },
    "28D": {
      "0": [0, 0, 1],
      "2": [0, 0, 1],
      "4": [1, 0, 1],
      "6": [1, 0, 1],
      "8": [1, 0, 1]
    },
    "28E": {
      "0": [0, 0, 1],
      "2": [0, 0, 1],
      "4": [1, 0, 1],
      "6": [1, 0, 1],
      "8": [1, 0, 1]
    },
    "28F": {
      "0": [0, 0, 1],
      "2": [0, 0, 1],
      "4": [1, 0, 1],
      "6": [1, 0, 1],
      "8": [1, 0, 1]
    },
    "29A": {
      "0": [0, 0, 1],
      "2": [0, 0, 1],
      "4": [1, 0, 1],
      "6": [1, 0, 1],
      "8": [1, 0, 1]
    },
    "29B": {
      "0": [0, 0, 1],
      "2": [0, 0, 1],
      "4": [1, 0, 1],
      "6": [1, 0, 1],
      "8": [1, 0, 1]
    },
    "29C": {
      "0": [0, 0, 1],
      "2": [0, 0, 1],
      "4": [1, 0, 1],
      "6": [1, 0, 1],
      "8": [1, 0, 1]
    },
    "29D": {
      "0": [0, 0, 1],
      "2": [0, 0, 1],
      "4": [1, 0, 1],
      "6": [1, 0, 1],
      "8": [1, 0, 1]
    },
    "29E": {
      "0": [0, 0, 1],
      "2": [0, 0, 1],
      "4": [1, 0, 1],
      "6": [1, 0, 1],
      "8": [1, 0, 1]
    },
    "29F": {
      "0": [0, 0, 1],
      "2": [0, 0, 1],
      "4": [1, 0, 1],
      "6": [1, 0, 1],
      "8": [1, 0, 1]
    },
    "29G": {
      "0": [0, 0, 1],
      "2": [0, 0, 1],
      "4": [1, 0, 1],
      "6": [1, 0, 1],
      "8": [1, 0, 1]
    },
    "30A": {
      "0": [0, 0, 1],
      "2": [0, 0, 1],
      "4": [1, 0, 1],
      "6": [1, 0, 1],
      "8": [1, 0, 1]
    },
    "30B": {
      "0": [0, 0, 1],
      "2": [0, 0, 1],
      "4": [1, 0, 1],
      "6": [1, 0, 1],
      "8": [1, 0, 1]
    },
    "30C": {
      "0": [0, 0, 1],
      "2": [0, 0, 1],
      "4": [1, 0, 1],
      "6": [1, 0, 1],
      "8": [1, 0, 1]
    },
    "30D": {
      "0": [0, 0, 1],
      "2": [0, 0, 1],
      "4": [1, 0, 1],
      "6": [1, 0, 1],
      "8": [1, 0, 1]
    },
    "30E": {
      "0": [0, 0, 1],
      "2": [0, 0, 1],
      "4": [1, 0, 1],
      "6": [1, 0, 1],
      "8": [1, 0, 1]
    },
    "30F": {
      "0": [0, 0, 1],
      "2": [0, 0, 1],
      "4": [1, 0, 1],
      "6": [1, 0, 1],
      "8": [1, 0, 1]
    },
    "32A": {
      "0": [0, 0, 1],
      "2": [0, 0, 1],
      "4": [1, 0, 1],
      "6": [1, 0, 1],
      "8": [1, 0, 1]
    },
    "32B": {
      "0": [0, 0, 1],
      "2": [0, 0, 1],
      "4": [1, 0, 1],
      "6": [1, 0, 1],
      "8": [1, 0, 1]
    },
    "32C": {
      "0": [0, 0, 1],
      "2": [0, 0, 1],
      "4": [1, 0, 1],
      "6": [1, 0, 1],
      "8": [1, 0, 1]
    },
    "32D": {
      "0": [0, 0, 1],
      "2": [0, 0, 1],
      "4": [1, 0, 1],
      "6": [1, 0, 1],
      "8": [1, 0, 1]
    },
    "32E": {
      "0": [0, 0, 1],
      "2": [0, 0, 1],
      "4": [1, 0, 1],
      "6": [1, 0, 1],
      "8": [1, 0, 1]
    },
    "32F": {
      "0": [0, 0, 1],
      "2": [0, 0, 1],
      "4": [1, 0, 1],
      "6": [1, 0, 1],
      "8": [1, 0, 1]
    },
    "34A": {
      "0": [0, 0, 1],
      "2": [0, 0, 1],
      "4": [1, 0, 1],
      "6": [1, 0, 1],
      "8": [1, 0, 1]
    },
    "34B": {
      "0": [0, 0, 1],
      "2": [0, 0, 1],
      "4": [1, 0, 1],
      "6": [1, 0, 1],
      "8": [1, 0, 1]
    },
    "34C": {
      "0": [0, 0, 1],
      "2": [0, 0, 1],
      "4": [1, 0, 1],
      "6": [1, 0, 1],
      "8": [1, 0, 1]
    },
    "34D": {
      "0": [0, 0, 1],
      "2": [0, 0, 1],
      "4": [1, 0, 1],
      "6": [1, 0, 1],
      "8": [1, 0, 1]
    },
    "34E": {
      "0": [0, 0, 1],
      "2": [0, 0, 1],
      "4": [1, 0, 1],
      "6": [1, 0, 1],
      "8": [1, 0, 1]
    },
    "34F": {
      "0": [0, 0, 1],
      "2": [0, 0, 1],
      "4": [1, 0, 1],
      "6": [1, 0, 1],
      "8": [1, 0, 1]
    },
    "34G": {
      "0": [0, 0, 1],
      "2": [0, 0, 1],
      "4": [1, 0, 1],
      "6": [1, 0, 1],
      "8": [1, 0, 1]
    },
    "34H": {
      "0": [0, 0, 1],
      "2": [0, 0, 1],
      "4": [1, 0, 1],
      "6": [1, 0, 1],
      "8": [1, 0, 1]
    },
    "34I": {
      "0": [0, 0, 1],
      "2": [0, 0, 1],
      "4": [1, 0, 1],
      "6": [1, 0, 1],
      "8": [1, 0, 1]
    },
    "34K": {
      "0": [0, 0, 1],
      "2": [0, 0, 1],
      "4": [1, 0, 1],
      "6": [1, 0, 1],
      "8": [1, 0, 1]
    },
    "36A": {
      "0": [0, 0, 1],
      "2": [0, 0, 1],
      "4": [1, 0, 1],
      "6": [1, 0, 1],
      "8": [1, 0, 1]
    },
    "36B": {
      "0": [0, 0, 1],
      "2": [0, 0, 1],
      "4": [1, 0, 1],
      "6": [1, 0, 1],
      "8": [1, 0, 1]
    },
    "36C": {
      "0": [0, 0, 1],
      "2": [0, 0, 1],
      "4": [1, 0, 1],
      "6": [1, 0, 1],
      "8": [1, 0, 1]
    },
    "36D": {
      "0": [0, 0, 1],
      "2": [0, 0, 1],
      "4": [1, 0, 1],
      "6": [1, 0, 1],
      "8": [1, 0, 1]
    },
    "36E": {
      "0": [0, 0, 1],
      "2": [0, 0, 1],
      "4": [1, 0, 1],
      "6": [1, 0, 1],
      "8": [1, 0, 1]
    },
    "36F": {
      "0": [0, 0, 1],
      "2": [0, 0, 1],
      "4": [1, 0, 1],
      "6": [1, 0, 1],
      "8": [1, 0, 1]
    },
    "36G": {
      "0": [0, 0, 1],
      "2": [0, 0, 1],
      "4": [1, 0, 1],
      "6": [1, 0, 1],
      "8": [1, 0, 1]
    },
    "38A": {
      "0": [0, 0, 1],
      "2": [0, 0, 1],
      "4": [0, 0, 1],
      "6": [0, 0, 1],
      "8": [0, 0, 1]
    },
    "38B": {
      "0": [0, 0, 1],
      "2": [0, 0, 1],
      "4": [0, 0, 1],
      "6": [0, 0, 1],
      "8": [0, 0, 1]
    },
    "38C": {
      "0": [0, 0, 1],
      "2": [0, 0, 1],
      "4": [0, 0, 1],
      "6": [0, 0, 1],
      "8": [0, 0, 1]
    },
    "38D": {
      "0": [0, 0, 1],
      "2": [0, 0, 1],
      "4": [0, 0, 1],
      "6": [0, 0, 1],
      "8": [0, 0, 1]
    },
    "38E": {
      "0": [0, 0, 1],
      "2": [0, 0, 1],
      "4": [0, 0, 1],
      "6": [0, 0, 1],
      "8": [0, 0, 1]
    },
    "38F": {
      "0": [0, 0, 1],
      "2": [0, 0, 1],
      "4": [0, 0, 1],
      "6": [0, 0, 1],
      "8": [0, 0, 1]
    },
    "38G": {
      "0": [0, 0, 1],
      "2": [0, 0, 1],
      "4": [0, 0, 1],
      "6": [0, 0, 1],
      "8": [0, 0, 1]
    },
    "38H": {
      "0": [0, 0, 1],
      "2": [0, 0, 1],
      "4": [0, 0, 1],
      "6": [0, 0, 1],
      "8": [0, 0, 1]
    },
    "38I": {
      "0": [0, 0, 1],
      "2": [0, 0, 1],
      "4": [0, 0, 1],
      "6": [0, 0, 1],
      "8": [0, 0, 1]
    },
    "38K": {
      "0": [0, 0, 1],
      "2": [0, 0, 1],
      "4": [0, 0, 1],
      "6": [0, 0, 1],
      "8": [0, 0, 1]
    },
    "38L": {
      "0": [0, 0, 1],
      "2": [0, 0, 1],
      "4": [0, 0, 1],
      "6": [0, 0, 1],
      "8": [0, 0, 1]
    },
    "38M": {
      "0": [0, 0, 1],
      "2": [0, 0, 1],
      "4": [0, 0, 1],
      "6": [0, 0, 1],
      "8": [0, 0, 1]
    },
    "38N": {
      "0": [0, 0, 1],
      "2": [0, 0, 1],
      "4": [0, 0, 1],
      "6": [0, 0, 1],
      "8": [0, 0, 1]
    },
    "38P": {
      "0": [0, 0, 1],
      "2": [0, 0, 1],
      "4": [0, 0, 1],
      "6": [0, 0, 1],
      "8": [0, 0, 1]
    },
    "38R": {
      "0": [0, 0, 1],
      "2": [0, 0, 1],
      "4": [0, 0, 1],
      "6": [0, 0, 1],
      "8": [0, 0, 1]
    },
    "38S": {
      "0": [0, 0, 1],
      "2": [0, 0, 1],
      "4": [0, 0, 1],
      "6": [0, 0, 1],
      "8": [0, 0, 1]
    },
    "38T": {
      "0": [0, 0, 1],
      "2": [0, 0, 1],
      "4": [0, 0, 1],
      "6": [0, 0, 1],
      "8": [0, 0, 1]
    },
    "38U": {
      "0": [0, 0, 1],
      "2": [0, 0, 1],
      "4": [0, 0, 1],
      "6": [0, 0, 1],
      "8": [0, 0, 1]
    },
    "38V": {
      "0": [0, 0, 1],
      "2": [0, 0, 1],
      "4": [0, 0, 1],
      "6": [0, 0, 1],
      "8": [0, 0, 1]
    },
    "40A": {
      "0": [0, 0, 1],
      "2": [0, 0, 1],
      "4": [0, 0, 1],
      "6": [0, 0, 1],
      "8": [0, 0, 1]
    },
    "40B": {
      "0": [0, 0, 1],
      "2": [0, 0, 1],
      "4": [0, 0, 1],
      "6": [0, 0, 1],
      "8": [0, 0, 1]
    },
    "40C": {
      "0": [0, 0, 1],
      "2": [0, 0, 1],
      "4": [0, 0, 1],
      "6": [0, 0, 1],
      "8": [0, 0, 1]
    },
    "40D": {
      "0": [0, 0, 1],
      "2": [0, 0, 1],
      "4": [0, 0, 1],
      "6": [0, 0, 1],
      "8": [0, 0, 1]
    },
    "40E": {
      "0": [0, 0, 1],
      "2": [0, 0, 1],
      "4": [0, 0, 1],
      "6": [0, 0, 1],
      "8": [0, 0, 1]
    },
    "40F": {
      "0": [0, 0, 1],
      "2": [0, 0, 1],
      "4": [0, 0, 1],
      "6": [0, 0, 1],
      "8": [0, 0, 1]
    },
    "40G": {
      "0": [0, 0, 1],
      "2": [0, 0, 1],
      "4": [0, 0, 1],
      "6": [0, 0, 1],
      "8": [0, 0, 1]
    },
    "40H": {
      "0": [0, 0, 1],
      "2": [0, 0, 1],
      "4": [0, 0, 1],
      "6": [0, 0, 1],
      "8": [0, 0, 1]
    },
    "40I": {
      "0": [0, 0, 1],
      "2": [0, 0, 1],
      "4": [0, 0, 1],
      "6": [0, 0, 1],
      "8": [0, 0, 1]
    },
    "40K": {
      "0": [0, 0, 1],
      "2": [0, 0, 1],
      "4": [0, 0, 1],
      "6": [0, 0, 1],
      "8": [0, 0, 1]
    },
    "40L": {
      "0": [0, 0, 1],
      "2": [0, 0, 1],
      "4": [0, 0, 1],
      "6": [0, 0, 1],
      "8": [0, 0, 1]
    },
    "40M": {
      "0": [0, 0, 1],
      "2": [0, 0, 1],
      "4": [0, 0, 1],
      "6": [0, 0, 1],
      "8": [0, 0, 1]
    },
    "40N": {
      "0": [0, 0, 1],
      "2": [0, 0, 1],
      "4": [0, 0, 1],
      "6": [0, 0, 1],
      "8": [0, 0, 1]
    },
    "42A": {
      "0": [0, 0, 1],
      "2": [0, 0, 1],
      "4": [0, 0, 1],
      "6": [0, 0, 1],
      "8": [0, 0, 1]
    },
    "42B": {
      "0": [0, 0, 1],
      "2": [0, 0, 1],
      "4": [0, 0, 1],
      "6": [0, 0, 1],
      "8": [0, 0, 1]
    },
    "42C": {
      "0": [0, 0, 1],
      "2": [0, 0, 1],
      "4": [0, 0, 1],
      "6": [0, 0, 1],
      "8": [0, 0, 1]
    },
    "42D": {
      "0": [0, 0, 1],
      "2": [0, 0, 1],
      "4": [0, 0, 1],
      "6": [0, 0, 1],
      "8": [0, 0, 1]
    },
    "42E": {
      "0": [0, 0, 1],
      "2": [0, 0, 1],
      "4": [0, 0, 1],
      "6": [0, 0, 1],
      "8": [0, 0, 1]
    },
    "42F": {
      "0": [0, 0, 1],
      "2": [0, 0, 1],
      "4": [0, 0, 1],
      "6": [0, 0, 1],
      "8": [0, 0, 1]
    },
    "42G": {
      "0": [0, 0, 1],
      "2": [0, 0, 1],
      "4": [0, 0, 1],
      "6": [0, 0, 1],
      "8": [0, 0, 1]
    },
    "42H": {
      "0": [0, 0, 1],
      "2": [0, 0, 1],
      "4": [0, 0, 1],
      "6": [0, 0, 1],
      "8": [0, 0, 1]
    },
    "42I": {
      "0": [0, 0, 1],
      "2": [0, 0, 1],
      "4": [0, 0, 1],
      "6": [0, 0, 1],
      "8": [0, 0, 1]
    },
    "42K": {
      "0": [0, 0, 1],
      "2": [0, 0, 1],
      "4": [0, 0, 1],
      "6": [0, 0, 1],
      "8": [0, 0, 1]
    },
    "42L": {
      "0": [0, 0, 1],
      "2": [0, 0, 1],
      "4": [0, 0, 1],
      "6": [0, 0, 1],
      "8": [0, 0, 1]
    },
    "42M": {
      "0": [0, 0, 1],
      "2": [0, 0, 1],
      "4": [0, 0, 1],
      "6": [0, 0, 1],
      "8": [0, 0, 1]
    },
    "44A": {
      "0": [0, 0, 1],
      "2": [0, 0, 1],
      "4": [0, 0, 1],
      "6": [0, 0, 1],
      "8": [0, 0, 1]
    },
    "44B": {
      "0": [0, 0, 1],
      "2": [0, 0, 1],
      "4": [0, 0, 1],
      "6": [0, 0, 1],
      "8": [0, 0, 1]
    },
    "44C": {
      "0": [0, 0, 1],
      "2": [0, 0, 1],
      "4": [0, 0, 1],
      "6": [0, 0, 1],
      "8": [0, 0, 1]
    },
    "44D": {
      "0": [0, 0, 1],
      "2": [0, 0, 1],
      "4": [0, 0, 1],
      "6": [0, 0, 1],
      "8": [0, 0, 1]
    },
    "44E": {
      "0": [0, 0, 1],
      "2": [0, 0, 1],
      "4": [0, 0, 1],
      "6": [0, 0, 1],
      "8": [0, 0, 1]
    },
    "44F": {
      "0": [0, 0, 1],
      "2": [0, 0, 1],
      "4": [0, 0, 1],
      "6": [0, 0, 1],
      "8": [0, 0, 1]
    },
    "44G": {
      "0": [0, 0, 1],
      "2": [0, 0, 1],
      "4": [0, 0, 1],
      "6": [0, 0, 1],
      "8": [0, 0, 1]
    },
    "44H": {
      "0": [0, 0, 1],
      "2": [0, 0, 1],
      "4": [0, 0, 1],
      "6": [0, 0, 1],
      "8": [0, 0, 1]
    },
    "44I": {
      "0": [0, 0, 1],
      "2": [0, 0, 1],
      "4": [0, 0, 1],
      "6": [0, 0, 1],
      "8": [0, 0, 1]
    },
    "46A": {
      "0": [0, 0, 1],
      "2": [0, 0, 1],
      "4": [0, 0, 1],
      "6": [0, 0, 1],
      "8": [0, 0, 1]
    },
    "46B": {
      "0": [0, 0, 1],
      "2": [0, 0, 1],
      "4": [0, 0, 1],
      "6": [0, 0, 1],
      "8": [0, 0, 1]
    },
    "46C": {
      "0": [0, 0, 1],
      "2": [0, 0, 1],
      "4": [0, 0, 1],
      "6": [0, 0, 1],
      "8": [0, 0, 1]
    },
    "46D": {
      "0": [0, 0, 1],
      "2": [0, 0, 1],
      "4": [0, 0, 1],
      "6": [0, 0, 1],
      "8": [0, 0, 1]
    },
    "46E": {
      "0": [0, 0, 1],
      "2": [0, 0, 1],
      "4": [0, 0, 1],
      "6": [0, 0, 1],
      "8": [0, 0, 1]
    },
    "46F": {
      "0": [0, 0, 1],
      "2": [0, 0, 1],
      "4": [0, 0, 1],
      "6": [0, 0, 1],
      "8": [0, 0, 1]
    },
    "46G": {
      "0": [0, 0, 1],
      "2": [0, 0, 1],
      "4": [0, 0, 1],
      "6": [0, 0, 1],
      "8": [0, 0, 1]
    },
    "46H": {
      "0": [0, 0, 1],
      "2": [0, 0, 1],
      "4": [0, 0, 1],
      "6": [0, 0, 1],
      "8": [0, 0, 1]
    },
    "46I": {
      "0": [0, 0, 1],
      "2": [0, 0, 1],
      "4": [0, 0, 1],
      "6": [0, 0, 1],
      "8": [0, 0, 1]
    },
    "46K": {
      "0": [0, 0, 1],
      "2": [0, 0, 1],
      "4": [0, 0, 1],
      "6": [0, 0, 1],
      "8": [0, 0, 1]
    },
    "46L": {
      "0": [0, 0, 1],
      "2": [0, 0, 1],
      "4": [0, 0, 1],
      "6": [0, 0, 1],
      "8": [0, 0, 1]
    },
    "46M": {
      "0": [0, 0, 1],
      "2": [0, 0, 1],
      "4": [0, 0, 1],
      "6": [0, 0, 1],
      "8": [0, 0, 1]
    },
    "46N": {
      "0": [0, 0, 1],
      "2": [0, 0, 1],
      "4": [0, 0, 1],
      "6": [0, 0, 1],
      "8": [0, 0, 1]
    },
    "46P": {
      "0": [0, 0, 1],
      "2": [0, 0, 1],
      "4": [0, 0, 1],
      "6": [0, 0, 1],
      "8": [0, 0, 1]
    },
    "46R": {
      "0": [0, 0, 1],
      "2": [0, 0, 1],
      "4": [0, 0, 1],
      "6": [0, 0, 1],
      "8": [0, 0, 1]
    },
    "46S": {
      "0": [0, 0, 1],
      "2": [0, 0, 1],
      "4": [0, 0, 1],
      "6": [0, 0, 1],
      "8": [0, 0, 1]
    },
    "47A": {
      "0": [0, 0, 1],
      "2": [0, 0, 1],
      "4": [1, 0, 1],
      "6": [1, 0, 1],
      "8": [1, 0, 1]
    },
    "47B": {
      "0": [0, 0, 1],
      "2": [0, 0, 1],
      "4": [1, 0, 1],
      "6": [1, 0, 1],
      "8": [1, 0, 1]
    },
    "47C": {
      "0": [0, 0, 1],
      "2": [0, 0, 1],
      "4": [1, 0, 1],
      "6": [1, 0, 1],
      "8": [1, 0, 1]
    },
    "47D": {
      "0": [0, 0, 1],
      "2": [0, 0, 1],
      "4": [1, 0, 1],
      "6": [1, 0, 1],
      "8": [1, 0, 1]
    },
    "47E": {
      "0": [0, 0, 1],
      "2": [0, 0, 1],
      "4": [1, 0, 1],
      "6": [1, 0, 1],
      "8": [1, 0, 1]
    },
    "47F": {
      "0": [0, 0, 1],
      "2": [0, 0, 1],
      "4": [1, 0, 1],
      "6": [1, 0, 1],
      "8": [1, 0, 1]
    },
    "47G": {
      "0": [0, 0, 1],
      "2": [0, 0, 1],
      "4": [1, 0, 1],
      "6": [1, 0, 1],
      "8": [1, 0, 1]
    },
    "48A": {
      "0": [0, 0, 1],
      "2": [0, 0, 1],
      "4": [0, 0, 1],
      "6": [0, 0, 1],
      "8": [0, 0, 1]
    },
    "48B": {
      "0": [0, 0, 1],
      "2": [0, 0, 1],
      "4": [0, 0, 1],
      "6": [0, 0, 1],
      "8": [0, 0, 1]
    },
    "48C": {
      "0": [0, 0, 1],
      "2": [0, 0, 1],
      "4": [0, 0, 1],
      "6": [0, 0, 1],
      "8": [0, 0, 1]
    },
    "48D": {
      "0": [0, 0, 1],
      "2": [0, 0, 1],
      "4": [0, 0, 1],
      "6": [0, 0, 1],
      "8": [0, 0, 1]
    },
    "48E": {
      "0": [0, 0, 1],
      "2": [0, 0, 1],
      "4": [0, 0, 1],
      "6": [0, 0, 1],
      "8": [0, 0, 1]
    },
    "48F": {
      "0": [0, 0, 1],
      "2": [0, 0, 1],
      "4": [0, 0, 1],
      "6": [0, 0, 1],
      "8": [0, 0, 1]
    },
    "48G": {
      "0": [0, 0, 1],
      "2": [0, 0, 1],
      "4": [0, 0, 1],
      "6": [0, 0, 1],
      "8": [0, 0, 1]
    },
    "48H": {
      "0": [0, 0, 1],
      "2": [0, 0, 1],
      "4": [0, 0, 1],
      "6": [0, 0, 1],
      "8": [0, 0, 1]
    },
    "48I": {
      "0": [0, 0, 1],
      "2": [0, 0, 1],
      "4": [0, 0, 1],
      "6": [0, 0, 1],
      "8": [0, 0, 1]
    },
    "48K": {
      "0": [0, 0, 1],
      "2": [0, 0, 1],
      "4": [0, 0, 1],
      "6": [0, 0, 1],
      "8": [0, 0, 1]
    },
    "48L": {
      "0": [0, 0, 1],
      "2": [0, 0, 1],
      "4": [0, 0, 1],
      "6": [0, 0, 1],
      "8": [0, 0, 1]
    },
    "48M": {
      "0": [0, 0, 1],
      "2": [0, 0, 1],
      "4": [0, 0, 1],
      "6": [0, 0, 1],
      "8": [0, 0, 1]
    },
    "48N": {
      "0": [0, 0, 1],
      "2": [0, 0, 1],
      "4": [0, 0, 1],
      "6": [0, 0, 1],
      "8": [0, 0, 1]
    },
    "48P": {
      "0": [0, 0, 1],
      "2": [0, 0, 1],
      "4": [0, 0, 1],
      "6": [0, 0, 1],
      "8": [0, 0, 1]
    },
    "48R": {
      "0": [0, 0, 1],
      "2": [0, 0, 1],
      "4": [0, 0, 1],
      "6": [0, 0, 1],
      "8": [0, 0, 1]
    },
    "48S": {
      "0": [0, 0, 1],
      "2": [0, 0, 1],
      "4": [0, 0, 1],
      "6": [0, 0, 1],
      "8": [0, 0, 1]
    },
    "48T": {
      "0": [0, 0, 1],
      "2": [0, 0, 1],
      "4": [0, 0, 1],
      "6": [0, 0, 1],
      "8": [0, 0, 1]
    },
    "48U": {
      "0": [0, 0, 1],
      "2": [0, 0, 1],
      "4": [0, 0, 1],
      "6": [0, 0, 1],
      "8": [0, 0, 1]
    },
    "48V": {
      "0": [0, 0, 1],
      "2": [0, 0, 1],
      "4": [0, 0, 1],
      "6": [0, 0, 1],
      "8": [0, 0, 1]
    },
    "48W": {
      "0": [0, 0, 1],
      "2": [0, 0, 1],
      "4": [0, 0, 1],
      "6": [0, 0, 1],
      "8": [0, 0, 1]
    },
    "48X": {
      "0": [0, 0, 1],
      "2": [0, 0, 1],
      "4": [0, 0, 1],
      "6": [0, 0, 1],
      "8": [0, 0, 1]
    },
    "65A": {
      "0": [0, 0, 1],
      "2": [0, 0, 1],
      "4": [0, 0, 1],
      "6": [0, 0, 1],
      "8": [0, 0, 1]
    },
    "68A": {
      "0": [0, 0, 1],
      "2": [0, 0, 1],
      "4": [0, 0, 1],
      "6": [0, 0, 1],
      "8": [0, 0, 1]
    },
    "75A": {
      "0": [0, 0, 1],
      "2": [0, 0, 1],
      "4": [0, 0, 1],
      "6": [0, 0, 1],
      "8": [0, 0, 1]
    },
    "76A": {
      "0": [0, 0, 1],
      "2": [0, 0, 1],
      "4": [0, 0, 1],
      "6": [0, 0, 1],
      "8": [0, 0, 1]
    },
    "77A": {
      "0": [0, 0, 1],
      "2": [0, 0, 1],
      "4": [0, 0, 1],
      "6": [0, 0, 1],
      "8": [0, 0, 1]
    },
    "79A": {
      "0": [0, 0, 1],
      "2": [0, 0, 1],
      "4": [0, 0, 1],
      "6": [0, 0, 1],
      "8": [0, 0, 1]
    },
    "80A": {
      "0": [0, 0, 1],
      "2": [0, 0, 1],
      "4": [0, 0, 1],
      "6": [0, 0, 1],
      "8": [0, 0, 1]
    },
    "87A": {
      "0": [0, 0, 1],
      "2": [0, 0, 1],
      "4": [0, 0, 1],
      "6": [0, 0, 1],
      "8": [0, 0, 1]
    }
  }
}
