{
  "13593": {
    "1": {
      "0": [0, 1, 0],
      "2": [0, 1, 0],
      "4": [0, 1, 0],
      "6": [0, 1, 0],
      "8": [0, 1, 0]
    },
    "3": {
      "0": [0, 0, 0],
      "2": [0, 0, 0],
      "4": [0, 0, 0],
      "6": [0, 0, 0],
      "8": [0, 0, 0]
    },
    "5": {
      "0": [0, 1, 0],
      "2": [0, 1, 0],
      "4": [0, 1, 0],
      "6": [0, 1, 0],
      "8": [0, 1, 0]
    },
    "7": {
      "0": [0, 0, 0],
      "2": [0, 0, 0],
      "4": [0, 0, 0],
      "6": [0, 0, 0],
      "8": [0, 0, 0]
    },
    "9": {
      "0": [0, 0, 0],
      "2": [0, 0, 0],
      "4": [0, 0, 0],
      "6": [0, 0, 0],
      "8": [0, 0, 0]
    },
    "10": {
      "0": [0, 0, 0],
      "2": [0, 0, 0],
      "4": [0, 0, 0],
      "6": [0, 0, 0],
      "8": [0, 0, 0]
    },
    "11": {
      "0": [0, 0, 0],
      "2": [0, 0, 0],
      "4": [0, 0, 0],
      "6": [0, 0, 0],
      "8": [0, 0, 0]
    },
    "12": {
      "0": [0, 0, 0],
      "2": [0, 0, 0],
      "4": [0, 0, 0],
      "6": [0, 0, 0],
      "8": [0, 0, 0]
    },
    "13": {
      "0": [0, 0, 0],
      "2": [0, 0, 0],
      "4": [0, 0, 0],
      "6": [0, 0, 0],
      "8": [0, 0, 0]
    },
    "14": {
      "0": [0, 0, 0],
      "2": [0, 0, 0],
      "4": [0, 0, 0],
      "6": [0, 0, 0],
      "8": [0, 0, 0]
    },
    "15": {
      "0": [0, 0, 0],
      "2": [0, 0, 0],
      "4": [0, 0, 0],
      "6": [0, 0, 0],
      "8": [0, 0, 0]
    },
    "16": {
      "0": [0, 0, 0],
      "2": [0, 0, 0],
      "4": [0, 0, 0],
      "6": [0, 0, 0],
      "8": [0, 0, 0]
    },
    "18": {
      "0": [0, 0, 0],
      "2": [0, 0, 0],
      "4": [0, 0, 0],
      "6": [0, 0, 0],
      "8": [0, 0, 0]
    },
    "19": {
      "0": [0, 0, 0],
      "2": [0, 0, 0],
      "4": [0, 0, 0],
      "6": [0, 0, 0],
      "8": [0, 0, 0]
    },
    "21": { "0": [0, 0, 0], "2": [0, 0, 0], "6": [0, 0, 0], "8": [0, 0, 0] },
    "23": {
      "0": [0, 0, 0],
      "2": [0, 0, 0],
      "4": [0, 0, 0],
      "6": [0, 0, 0],
      "8": [0, 0, 0]
    },
    "27": { "6": [0, 0, 0], "8": [0, 0, 0] },
    "31": {
      "0": [0, 0, 0],
      "2": [0, 0, 0],
      "4": [0, 0, 0],
      "6": [0, 0, 0],
      "8": [0, 0, 0]
    },
    "33": {
      "0": [0, 0, 0],
      "2": [0, 0, 0],
      "4": [0, 0, 0],
      "6": [0, 0, 0],
      "8": [0, 0, 0]
    },
    "35": {
      "0": [0, 0, 0],
      "2": [0, 0, 0],
      "4": [0, 0, 0],
      "6": [0, 0, 0],
      "8": [0, 0, 0]
    },
    "37": {
      "0": [0, 0, 0],
      "2": [0, 0, 0],
      "4": [0, 0, 0],
      "6": [0, 0, 0],
      "8": [0, 0, 0]
    },
    "1A": { "2": [0, 0, 0], "4": [0, 1, 0], "6": [0, 1, 0], "8": [0, 1, 0] },
    "5A": {
      "0": [0, 0, 0],
      "2": [0, 0, 0],
      "4": [0, 0, 0],
      "6": [0, 0, 0],
      "8": [0, 0, 0]
    },
    "9A": {
      "0": [0, 0, 0],
      "2": [0, 0, 0],
      "4": [0, 0, 0],
      "6": [0, 0, 0],
      "8": [0, 0, 0]
    },
    "11A": {
      "0": [0, 0, 0],
      "2": [0, 0, 0],
      "4": [0, 0, 0],
      "6": [0, 0, 0],
      "8": [0, 0, 0]
    },
    "13A": {
      "0": [0, 0, 0],
      "2": [0, 0, 0],
      "4": [0, 0, 0],
      "6": [0, 0, 0],
      "8": [0, 0, 0]
    },
    "23B": {
      "0": [0, 0, 0],
      "2": [0, 0, 0],
      "4": [0, 0, 0],
      "6": [0, 0, 0],
      "8": [0, 0, 0]
    },
    "23C": {
      "0": [0, 0, 0],
      "2": [0, 0, 0],
      "4": [0, 0, 0],
      "6": [0, 0, 0],
      "8": [0, 0, 0]
    },
    "23D": {
      "0": [0, 0, 0],
      "2": [0, 0, 0],
      "4": [0, 0, 0],
      "6": [0, 0, 0],
      "8": [0, 0, 0]
    },
    "23F": {
      "0": [0, 0, 0],
      "2": [0, 0, 0],
      "4": [0, 0, 0],
      "6": [0, 0, 0],
      "8": [0, 0, 0]
    },
    "23G": {
      "0": [0, 0, 0],
      "2": [0, 0, 0],
      "4": [0, 0, 0],
      "6": [0, 0, 0],
      "8": [0, 0, 0]
    },
    "23H": {
      "0": [0, 0, 0],
      "2": [0, 0, 0],
      "4": [0, 0, 0],
      "6": [0, 0, 0],
      "8": [0, 0, 0]
    },
    "23J": {
      "0": [0, 0, 0],
      "2": [0, 0, 0],
      "4": [0, 0, 0],
      "6": [0, 0, 0],
      "8": [0, 0, 0]
    },
    "23K": {
      "0": [0, 0, 0],
      "2": [0, 0, 0],
      "4": [0, 0, 0],
      "6": [0, 0, 0],
      "8": [0, 0, 0]
    },
    "23L": {
      "0": [0, 0, 0],
      "2": [0, 0, 0],
      "4": [0, 0, 0],
      "6": [0, 0, 0],
      "8": [0, 0, 0]
    },
    "23M": {
      "0": [0, 0, 0],
      "2": [0, 0, 0],
      "4": [0, 0, 0],
      "6": [0, 0, 0],
      "8": [0, 0, 0]
    },
    "23N": {
      "0": [0, 0, 0],
      "2": [0, 0, 0],
      "4": [0, 0, 0],
      "6": [0, 0, 0],
      "8": [0, 0, 0]
    },
    "23P": {
      "0": [0, 0, 0],
      "2": [0, 0, 0],
      "4": [0, 0, 0],
      "6": [0, 0, 0],
      "8": [0, 0, 0]
    },
    "23T": {
      "0": [0, 0, 0],
      "2": [0, 0, 0],
      "4": [0, 0, 0],
      "6": [0, 0, 0],
      "8": [0, 0, 0]
    },
    "23V": {
      "0": [0, 0, 0],
      "2": [0, 0, 0],
      "4": [0, 0, 0],
      "6": [0, 0, 0],
      "8": [0, 0, 0]
    },
    "25C": {
      "0": [0, 0, 0],
      "2": [0, 0, 0],
      "4": [0, 0, 0],
      "6": [0, 0, 0],
      "8": [0, 0, 0]
    },
    "25E": {
      "0": [0, 0, 0],
      "2": [0, 0, 0],
      "4": [0, 0, 0],
      "6": [0, 0, 0],
      "8": [0, 0, 0]
    },
    "25F": {
      "0": [0, 0, 0],
      "2": [0, 0, 0],
      "4": [0, 0, 0],
      "6": [0, 0, 0],
      "8": [0, 0, 0]
    },
    "25G": {
      "0": [0, 0, 0],
      "2": [0, 0, 0],
      "4": [0, 0, 0],
      "6": [0, 0, 0],
      "8": [0, 0, 0]
    },
    "25K": {
      "0": [0, 0, 0],
      "2": [0, 0, 0],
      "4": [0, 0, 0],
      "6": [0, 0, 0],
      "8": [0, 0, 0]
    },
    "25N": {
      "0": [0, 0, 0],
      "2": [0, 0, 0],
      "4": [0, 0, 0],
      "6": [0, 0, 0],
      "8": [0, 0, 0]
    },
    "25Q": {
      "0": [0, 0, 0],
      "2": [0, 0, 0],
      "4": [0, 0, 0],
      "6": [0, 0, 0],
      "8": [0, 0, 0]
    },
    "25S": {
      "0": [0, 0, 0],
      "2": [0, 0, 0],
      "4": [0, 0, 0],
      "6": [0, 0, 0],
      "8": [0, 0, 0]
    },
    "25T": {
      "0": [0, 0, 0],
      "2": [0, 0, 0],
      "4": [0, 0, 0],
      "6": [0, 0, 0],
      "8": [0, 0, 0]
    },
    "25U": {
      "0": [0, 0, 0],
      "2": [0, 0, 0],
      "4": [0, 0, 0],
      "6": [0, 0, 0],
      "8": [0, 0, 0]
    },
    "31A": {
      "0": [0, 0, 0],
      "2": [0, 0, 0],
      "4": [0, 0, 0],
      "6": [0, 0, 0],
      "8": [0, 0, 0]
    },
    "31B": {
      "0": [0, 0, 0],
      "2": [0, 0, 0],
      "4": [0, 0, 0],
      "6": [0, 0, 0],
      "8": [0, 0, 0]
    },
    "31C": {
      "0": [0, 0, 0],
      "2": [0, 0, 0],
      "4": [0, 0, 0],
      "6": [0, 0, 0],
      "8": [0, 0, 0]
    },
    "21A": { "6": [0, 0, 0], "8": [0, 0, 0] },
    "21B": { "6": [0, 0, 0], "8": [0, 0, 0] },
    "21C": { "6": [0, 0, 0], "8": [0, 0, 0] },
    "21D": { "6": [0, 0, 0], "8": [0, 0, 0] },
    "21E": { "6": [0, 0, 0], "8": [0, 0, 0] },
    "27A": { "6": [0, 0, 0], "8": [0, 0, 0] },
    "27B": { "6": [0, 0, 0], "8": [0, 0, 0] }
  }
}
